[
  {
    "id": "PremierLeague-Bournemouth-Fulham",
    "league": "Premier League",
    "team1": {
      "name": "Bournemouth"
    },
    "team2": {
      "name": "Fulham"
    },
    "kickoff_date": "2025-10-04",
    "kickoff_time": "02:00",
    "match_date": "2025-10-04",
    "match_time": "01:50",
    "duration": "3.5",
    "servers": [
      {
        "url": "https://multi.govoet.my.id/?ss=hd1",
        "label": "CH-1"
      },
      {
        "url": "https://multi.govoet.my.id/?ss=eleven1",
        "label": "CH-2"
      },
      {
        "url": "https://multi.govoet.my.id/?ss=br2",
        "label": "CH-3"
      }
    ]
  },
  {
    "id": "PremierLeague-Leeds-Tottenham",
    "league": "Premier League",
    "team1": {
      "name": "Leeds"
    },
    "team2": {
      "name": "Tottenham"
    },
    "kickoff_date": "2025-10-04",
    "kickoff_time": "18:30",
    "match_date": "2025-10-04",
    "match_time": "18:20",
    "duration": "3.5",
    "servers": []
  },
  {
    "id": "PremierLeague-Arsenal-WestHam",
    "league": "Premier League",
    "team1": {
      "name": "Arsenal"
    },
    "team2": {
      "name": "West Ham"
    },
    "kickoff_date": "2025-10-04",
    "kickoff_time": "21:00",
    "match_date": "2025-10-04",
    "match_time": "20:50",
    "duration": "3.5",
    "servers": []
  },
  {
    "id": "PremierLeague-ManchesterUtd-Sunderland",
    "league": "Premier League",
    "team1": {
      "name": "Manchester Utd"
    },
    "team2": {
      "name": "Sunderland"
    },
    "kickoff_date": "2025-10-04",
    "kickoff_time": "21:00",
    "match_date": "2025-10-04",
    "match_time": "20:50",
    "duration": "3.5",
    "servers": []
  },
  {
    "id": "PremierLeague-Chelsea-Liverpool",
    "league": "Premier League",
    "team1": {
      "name": "Chelsea"
    },
    "team2": {
      "name": "Liverpool"
    },
    "kickoff_date": "2025-10-04",
    "kickoff_time": "23:30",
    "match_date": "2025-10-04",
    "match_time": "23:20",
    "duration": "3.5",
    "servers": []
  },
  {
    "id": "PremierLeague-AstonVilla-Burnley",
    "league": "Premier League",
    "team1": {
      "name": "Aston Villa"
    },
    "team2": {
      "name": "Burnley"
    },
    "kickoff_date": "2025-10-05",
    "kickoff_time": "20:00",
    "match_date": "2025-10-05",
    "match_time": "19:50",
    "duration": "3.5",
    "servers": []
  },
  {
    "id": "PremierLeague-Everton-CrystalPalace",
    "league": "Premier League",
    "team1": {
      "name": "Everton"
    },
    "team2": {
      "name": "Crystal Palace"
    },
    "kickoff_date": "2025-10-05",
    "kickoff_time": "20:00",
    "match_date": "2025-10-05",
    "match_time": "19:50",
    "duration": "3.5",
    "servers": []
  },
  {
    "id": "PremierLeague-Newcastle-Nottingham",
    "league": "Premier League",
    "team1": {
      "name": "Newcastle"
    },
    "team2": {
      "name": "Nottingham"
    },
    "kickoff_date": "2025-10-05",
    "kickoff_time": "20:00",
    "match_date": "2025-10-05",
    "match_time": "19:50",
    "duration": "3.5",
    "servers": []
  },
  {
    "id": "PremierLeague-Wolves-Brighton",
    "league": "Premier League",
    "team1": {
      "name": "Wolves"
    },
    "team2": {
      "name": "Brighton"
    },
    "kickoff_date": "2025-10-05",
    "kickoff_time": "20:00",
    "match_date": "2025-10-05",
    "match_time": "19:50",
    "duration": "3.5",
    "servers": []
  },
  {
    "id": "PremierLeague-Brentford-ManchesterCity",
    "league": "Premier League",
    "team1": {
      "name": "Brentford"
    },
    "team2": {
      "name": "Manchester City"
    },
    "kickoff_date": "2025-10-05",
    "kickoff_time": "22:30",
    "match_date": "2025-10-05",
    "match_time": "22:20",
    "duration": "3.5",
    "servers": []
  },
  {
    "id": "Eredivisie-NACBreda-Groningen",
    "league": "Eredivisie",
    "team1": {
      "name": "NAC Breda"
    },
    "team2": {
      "name": "Groningen"
    },
    "kickoff_date": "2025-10-04",
    "kickoff_time": "01:00",
    "match_date": "2025-10-04",
    "match_time": "00:50",
    "duration": "3.5",
    "servers": [
      {
        "url": "https://multi.govoet.my.id/?ss=hd9",
        "label": "CH-1"
      }
    ]
  },
  {
    "id": "Eredivisie-SpartaRotterdam-Ajax",
    "league": "Eredivisie",
    "team1": {
      "name": "Sparta Rotterdam"
    },
    "team2": {
      "name": "Ajax"
    },
    "kickoff_date": "2025-10-04",
    "kickoff_time": "21:30",
    "match_date": "2025-10-04",
    "match_time": "21:20",
    "duration": "3.5",
    "servers": []
  },
  {
    "id": "Eredivisie-Sittard-FCVolendam",
    "league": "Eredivisie",
    "team1": {
      "name": "Sittard"
    },
    "team2": {
      "name": "FC Volendam"
    },
    "kickoff_date": "2025-10-04",
    "kickoff_time": "23:45",
    "match_date": "2025-10-04",
    "match_time": "23:35",
    "duration": "3.5",
    "servers": []
  },
  {
    "id": "Eredivisie-Zwolle-PSV",
    "league": "Eredivisie",
    "team1": {
      "name": "Zwolle"
    },
    "team2": {
      "name": "PSV"
    },
    "kickoff_date": "2025-10-05",
    "kickoff_time": "01:00",
    "match_date": "2025-10-05",
    "match_time": "00:50",
    "duration": "3.5",
    "servers": []
  },
  {
    "id": "Eredivisie-Heerenveen-Excelsior",
    "league": "Eredivisie",
    "team1": {
      "name": "Heerenveen"
    },
    "team2": {
      "name": "Excelsior"
    },
    "kickoff_date": "2025-10-05",
    "kickoff_time": "02:00",
    "match_date": "2025-10-05",
    "match_time": "01:50",
    "duration": "3.5",
    "servers": []
  },
  {
    "id": "Eredivisie-Twente-Heracles",
    "league": "Eredivisie",
    "team1": {
      "name": "Twente"
    },
    "team2": {
      "name": "Heracles"
    },
    "kickoff_date": "2025-10-05",
    "kickoff_time": "17:15",
    "match_date": "2025-10-05",
    "match_time": "17:05",
    "duration": "3.5",
    "servers": []
  },
  {
    "id": "Eredivisie-Feyenoord-Utrecht",
    "league": "Eredivisie",
    "team1": {
      "name": "Feyenoord"
    },
    "team2": {
      "name": "Utrecht"
    },
    "kickoff_date": "2025-10-05",
    "kickoff_time": "19:30",
    "match_date": "2025-10-05",
    "match_time": "19:20",
    "duration": "3.5",
    "servers": []
  },
  {
    "id": "Eredivisie-AZAlkmaar-Telstar",
    "league": "Eredivisie",
    "team1": {
      "name": "AZ Alkmaar"
    },
    "team2": {
      "name": "Telstar"
    },
    "kickoff_date": "2025-10-05",
    "kickoff_time": "21:45",
    "match_date": "2025-10-05",
    "match_time": "21:35",
    "duration": "3.5",
    "servers": []
  },
  {
    "id": "Ligue1-ParisFC-Lorient",
    "league": "Ligue 1",
    "team1": {
      "name": "Paris FC"
    },
    "team2": {
      "name": "Lorient"
    },
    "kickoff_date": "2025-10-04",
    "kickoff_time": "01:45",
    "match_date": "2025-10-04",
    "match_time": "01:35",
    "duration": "3.5",
    "servers": [
      {
        "url": "https://multi.govoet.my.id/?ss=hd4",
        "label": "CH-1"
      },
      {
        "url": "https://multi.govoet.my.id/?ss=sporttv3",
        "label": "CH-2"
      }
    ]
  },
  {
    "id": "Ligue1-Metz-Marseille",
    "league": "Ligue 1",
    "team1": {
      "name": "Metz"
    },
    "team2": {
      "name": "Marseille"
    },
    "kickoff_date": "2025-10-04",
    "kickoff_time": "22:00",
    "match_date": "2025-10-04",
    "match_time": "21:50",
    "duration": "3.5",
    "servers": []
  },
  {
    "id": "Ligue1-Brest-Nantes",
    "league": "Ligue 1",
    "team1": {
      "name": "Brest"
    },
    "team2": {
      "name": "Nantes"
    },
    "kickoff_date": "2025-10-05",
    "kickoff_time": "00:00",
    "match_date": "2025-10-04",
    "match_time": "23:50",
    "duration": "3.5",
    "servers": []
  },
  {
    "id": "Ligue1-Auxerre-Lens",
    "league": "Ligue 1",
    "team1": {
      "name": "Auxerre"
    },
    "team2": {
      "name": "Lens"
    },
    "kickoff_date": "2025-10-05",
    "kickoff_time": "02:05",
    "match_date": "2025-10-05",
    "match_time": "01:55",
    "duration": "3.5",
    "servers": []
  },
  {
    "id": "Ligue1-Lyon-Toulouse",
    "league": "Ligue 1",
    "team1": {
      "name": "Lyon"
    },
    "team2": {
      "name": "Toulouse"
    },
    "kickoff_date": "2025-10-05",
    "kickoff_time": "20:00",
    "match_date": "2025-10-05",
    "match_time": "19:50",
    "duration": "3.5",
    "servers": []
  },
  {
    "id": "Ligue1-LeHavre-Rennes",
    "league": "Ligue 1",
    "team1": {
      "name": "Le Havre"
    },
    "team2": {
      "name": "Rennes"
    },
    "kickoff_date": "2025-10-05",
    "kickoff_time": "22:15",
    "match_date": "2025-10-05",
    "match_time": "22:05",
    "duration": "3.5",
    "servers": []
  },
  {
    "id": "Ligue1-Monaco-Nice",
    "league": "Ligue 1",
    "team1": {
      "name": "Monaco"
    },
    "team2": {
      "name": "Nice"
    },
    "kickoff_date": "2025-10-05",
    "kickoff_time": "22:15",
    "match_date": "2025-10-05",
    "match_time": "22:05",
    "duration": "3.5",
    "servers": []
  },
  {
    "id": "Ligue1-Strasbourg-Angers",
    "league": "Ligue 1",
    "team1": {
      "name": "Strasbourg"
    },
    "team2": {
      "name": "Angers"
    },
    "kickoff_date": "2025-10-05",
    "kickoff_time": "22:15",
    "match_date": "2025-10-05",
    "match_time": "22:05",
    "duration": "3.5",
    "servers": []
  },
  {
    "id": "Bundesliga-Hoffenheim-FCKoln",
    "league": "Bundesliga",
    "team1": {
      "name": "Hoffenheim"
    },
    "team2": {
      "name": "FC Koln"
    },
    "kickoff_date": "2025-10-04",
    "kickoff_time": "01:30",
    "match_date": "2025-10-04",
    "match_time": "01:20",
    "duration": "3.5",
    "servers": []
  },
  {
    "id": "Bundesliga-Augsburg-Wolfsburg",
    "league": "Bundesliga",
    "team1": {
      "name": "Augsburg"
    },
    "team2": {
      "name": "Wolfsburg"
    },
    "kickoff_date": "2025-10-04",
    "kickoff_time": "20:30",
    "match_date": "2025-10-04",
    "match_time": "20:20",
    "duration": "3.5",
    "servers": []
  },
  {
    "id": "Bundesliga-BayerLeverkusen-UnionBerlin",
    "league": "Bundesliga",
    "team1": {
      "name": "Bayer Leverkusen"
    },
    "team2": {
      "name": "Union Berlin"
    },
    "kickoff_date": "2025-10-04",
    "kickoff_time": "20:30",
    "match_date": "2025-10-04",
    "match_time": "20:20",
    "duration": "3.5",
    "servers": []
  },
  {
    "id": "Bundesliga-Dortmund-RBLeipzig",
    "league": "Bundesliga",
    "team1": {
      "name": "Dortmund"
    },
    "team2": {
      "name": "RB Leipzig"
    },
    "kickoff_date": "2025-10-04",
    "kickoff_time": "20:30",
    "match_date": "2025-10-04",
    "match_time": "20:20",
    "duration": "3.5",
    "servers": []
  },
  {
    "id": "Bundesliga-WerderBremen-St.Pauli",
    "league": "Bundesliga",
    "team1": {
      "name": "Werder Bremen"
    },
    "team2": {
      "name": "St. Pauli"
    },
    "kickoff_date": "2025-10-04",
    "kickoff_time": "20:30",
    "match_date": "2025-10-04",
    "match_time": "20:20",
    "duration": "3.5",
    "servers": []
  },
  {
    "id": "Bundesliga-EintrachtFrankfurt-BayernMunich",
    "league": "Bundesliga",
    "team1": {
      "name": "Eintracht Frankfurt"
    },
    "team2": {
      "name": "Bayern Munich"
    },
    "kickoff_date": "2025-10-04",
    "kickoff_time": "23:30",
    "match_date": "2025-10-04",
    "match_time": "23:20",
    "duration": "3.5",
    "servers": []
  },
  {
    "id": "Bundesliga-Stuttgart-Heidenheim",
    "league": "Bundesliga",
    "team1": {
      "name": "Stuttgart"
    },
    "team2": {
      "name": "Heidenheim"
    },
    "kickoff_date": "2025-10-05",
    "kickoff_time": "20:30",
    "match_date": "2025-10-05",
    "match_time": "20:20",
    "duration": "3.5",
    "servers": []
  },
  {
    "id": "Bundesliga-HamburgerSV-Mainz",
    "league": "Bundesliga",
    "team1": {
      "name": "Hamburger SV"
    },
    "team2": {
      "name": "Mainz"
    },
    "kickoff_date": "2025-10-05",
    "kickoff_time": "22:30",
    "match_date": "2025-10-05",
    "match_time": "22:20",
    "duration": "3.5",
    "servers": []
  },
  {
    "id": "SerieA-Verona-Sassuolo",
    "league": "Serie A",
    "team1": {
      "name": "Verona"
    },
    "team2": {
      "name": "Sassuolo"
    },
    "kickoff_date": "2025-10-04",
    "kickoff_time": "01:45",
    "match_date": "2025-10-04",
    "match_time": "01:35",
    "duration": "3.5",
    "servers": []
  },
  {
    "id": "SerieA-Lazio-Torino",
    "league": "Serie A",
    "team1": {
      "name": "Lazio"
    },
    "team2": {
      "name": "Torino"
    },
    "kickoff_date": "2025-10-04",
    "kickoff_time": "20:00",
    "match_date": "2025-10-04",
    "match_time": "19:50",
    "duration": "3.5",
    "servers": []
  },
  {
    "id": "SerieA-Parma-Lecce",
    "league": "Serie A",
    "team1": {
      "name": "Parma"
    },
    "team2": {
      "name": "Lecce"
    },
    "kickoff_date": "2025-10-04",
    "kickoff_time": "20:00",
    "match_date": "2025-10-04",
    "match_time": "19:50",
    "duration": "3.5",
    "servers": []
  },
  {
    "id": "SerieA-Inter-Cremonese",
    "league": "Serie A",
    "team1": {
      "name": "Inter"
    },
    "team2": {
      "name": "Cremonese"
    },
    "kickoff_date": "2025-10-04",
    "kickoff_time": "23:00",
    "match_date": "2025-10-04",
    "match_time": "22:50",
    "duration": "3.5",
    "servers": []
  },
  {
    "id": "SerieA-Atalanta-Como",
    "league": "Serie A",
    "team1": {
      "name": "Atalanta"
    },
    "team2": {
      "name": "Como"
    },
    "kickoff_date": "2025-10-05",
    "kickoff_time": "01:45",
    "match_date": "2025-10-05",
    "match_time": "01:35",
    "duration": "3.5",
    "servers": []
  },
  {
    "id": "SerieA-Udinese-Cagliari",
    "league": "Serie A",
    "team1": {
      "name": "Udinese"
    },
    "team2": {
      "name": "Cagliari"
    },
    "kickoff_date": "2025-10-05",
    "kickoff_time": "17:30",
    "match_date": "2025-10-05",
    "match_time": "17:20",
    "duration": "3.5",
    "servers": []
  },
  {
    "id": "SerieA-Bologna-Pisa",
    "league": "Serie A",
    "team1": {
      "name": "Bologna"
    },
    "team2": {
      "name": "Pisa"
    },
    "kickoff_date": "2025-10-05",
    "kickoff_time": "20:00",
    "match_date": "2025-10-05",
    "match_time": "19:50",
    "duration": "3.5",
    "servers": []
  },
  {
    "id": "SerieA-Fiorentina-ASRoma",
    "league": "Serie A",
    "team1": {
      "name": "Fiorentina"
    },
    "team2": {
      "name": "AS Roma"
    },
    "kickoff_date": "2025-10-05",
    "kickoff_time": "20:00",
    "match_date": "2025-10-05",
    "match_time": "19:50",
    "duration": "3.5",
    "servers": []
  },
  {
    "id": "SerieA-Napoli-Genoa",
    "league": "Serie A",
    "team1": {
      "name": "Napoli"
    },
    "team2": {
      "name": "Genoa"
    },
    "kickoff_date": "2025-10-05",
    "kickoff_time": "23:00",
    "match_date": "2025-10-05",
    "match_time": "22:50",
    "duration": "3.5",
    "servers": []
  },
  {
    "id": "LaLiga-Osasuna-Getafe",
    "league": "LaLiga",
    "team1": {
      "name": "Osasuna"
    },
    "team2": {
      "name": "Getafe"
    },
    "kickoff_date": "2025-10-04",
    "kickoff_time": "02:00",
    "match_date": "2025-10-04",
    "match_time": "01:50",
    "duration": "3.5",
    "servers": [
      {
        "url": "https://multi.govoet.my.id/?ss=hd6",
        "label": "CH-1"
      },
      {
        "url": "https://multi.govoet.my.id/?ss=eleven2",
        "label": "CH-2"
      }
    ]
  },
  {
    "id": "LaLiga-R.Oviedo-Levante",
    "league": "LaLiga",
    "team1": {
      "name": "R. Oviedo"
    },
    "team2": {
      "name": "Levante"
    },
    "kickoff_date": "2025-10-04",
    "kickoff_time": "19:00",
    "match_date": "2025-10-04",
    "match_time": "18:50",
    "duration": "3.5",
    "servers": []
  },
  {
    "id": "LaLiga-Girona-Valencia",
    "league": "LaLiga",
    "team1": {
      "name": "Girona"
    },
    "team2": {
      "name": "Valencia"
    },
    "kickoff_date": "2025-10-04",
    "kickoff_time": "21:15",
    "match_date": "2025-10-04",
    "match_time": "21:05",
    "duration": "3.5",
    "servers": []
  },
  {
    "id": "LaLiga-AthBilbao-Mallorca",
    "league": "LaLiga",
    "team1": {
      "name": "Ath Bilbao"
    },
    "team2": {
      "name": "Mallorca"
    },
    "kickoff_date": "2025-10-04",
    "kickoff_time": "23:30",
    "match_date": "2025-10-04",
    "match_time": "23:20",
    "duration": "3.5",
    "servers": []
  },
  {
    "id": "LaLiga-RealMadrid-Villarreal",
    "league": "LaLiga",
    "team1": {
      "name": "Real Madrid"
    },
    "team2": {
      "name": "Villarreal"
    },
    "kickoff_date": "2025-10-05",
    "kickoff_time": "02:00",
    "match_date": "2025-10-05",
    "match_time": "01:50",
    "duration": "3.5",
    "servers": []
  },
  {
    "id": "LaLiga-Alaves-Elche",
    "league": "LaLiga",
    "team1": {
      "name": "Alaves"
    },
    "team2": {
      "name": "Elche"
    },
    "kickoff_date": "2025-10-05",
    "kickoff_time": "19:00",
    "match_date": "2025-10-05",
    "match_time": "18:50",
    "duration": "3.5",
    "servers": []
  },
  {
    "id": "LaLiga-Sevilla-Barcelona",
    "league": "LaLiga",
    "team1": {
      "name": "Sevilla"
    },
    "team2": {
      "name": "Barcelona"
    },
    "kickoff_date": "2025-10-05",
    "kickoff_time": "21:15",
    "match_date": "2025-10-05",
    "match_time": "21:05",
    "duration": "3.5",
    "servers": []
  },
  {
    "id": "LaLiga-Espanyol-Betis",
    "league": "LaLiga",
    "team1": {
      "name": "Espanyol"
    },
    "team2": {
      "name": "Betis"
    },
    "kickoff_date": "2025-10-05",
    "kickoff_time": "23:30",
    "match_date": "2025-10-05",
    "match_time": "23:20",
    "duration": "3.5",
    "servers": []
  },
  {
    "id": "LaLiga-RealSociedad-RayoVallecano",
    "league": "LaLiga",
    "team1": {
      "name": "Real Sociedad"
    },
    "team2": {
      "name": "Rayo Vallecano"
    },
    "kickoff_date": "2025-10-05",
    "kickoff_time": "23:30",
    "match_date": "2025-10-05",
    "match_time": "23:20",
    "duration": "3.5",
    "servers": []
  },
  {
    "id": "ChampionsLeague-Arsenal-OlympiacosPiraeus",
    "league": "Champions League",
    "team1": {
      "name": "Arsenal"
    },
    "team2": {
      "name": "Olympiacos Piraeus"
    },
    "kickoff_date": "2025-10-02",
    "kickoff_time": "02:00",
    "match_date": "2025-10-02",
    "match_time": "01:50",
    "duration": "3.5",
    "servers": [
      {
        "url": "https://multi.govoet.my.id/?envivo=13",
        "label": "CH-FR"
      },
      {
        "url": "https://multi.govoet.my.id/?envivo=166",
        "label": "CH-ES"
      },
      {
        "url": "https://multi.govoet.my.id/?envivo=126",
        "label": "CH-GB"
      },
      {
        "url": "https://multi.govoet.my.id/?envivo=91",
        "label": "CH-ES"
      },
      {
        "url": "https://multi.govoet.my.id/?ss=hd1",
        "label": "CH-1"
      },
      {
        "url": "https://multi.govoet.my.id/?ss=eleven2",
        "label": "CH-2"
      },
      {
        "url": "https://multi.govoet.my.id/?ss=br2",
        "label": "CH-3"
      },
      {
        "url": "https://multi.govoet.my.id/?shaka=espn2arg",
        "label": "CH-NL"
      },
      {
        "url": "https://multi.govoet.my.id/?shaka=tnt1",
        "label": "CH-EN"
      }
    ]
  },
  {
    "id": "ChampionsLeague-Barcelona-PSG",
    "league": "Champions League",
    "team1": {
      "name": "Barcelona"
    },
    "team2": {
      "name": "PSG"
    },
    "kickoff_date": "2025-10-02",
    "kickoff_time": "02:00",
    "match_date": "2025-10-02",
    "match_time": "01:50",
    "duration": "3.5",
    "servers": [
      {
        "url": "https://multi.govoet.my.id/?envivo=11",
        "label": "CH-FR"
      },
      {
        "url": "https://multi.govoet.my.id/?envivo=161",
        "label": "CH-ES"
      },
      {
        "url": "https://multi.govoet.my.id/?envivo=131",
        "label": "CH-GB"
      },
      {
        "url": "https://multi.govoet.my.id/?envivo=138",
        "label": "CH-IT"
      },
      {
        "url": "https://multi.govoet.my.id/?envivo=87",
        "label": "CH-ES"
      },
      {
        "url": "https://multi.govoet.my.id/?ss=hd5",
        "label": "CH-1"
      },
      {
        "url": "https://multi.govoet.my.id/?ss=hd4",
        "label": "CH-2"
      },
      {
        "url": "https://multi.govoet.my.id/?ss=hd6",
        "label": "CH-3"
      },
      {
        "url": "https://multi.govoet.my.id/?ss=hd9",
        "label": "CH-4"
      },
      {
        "url": "https://multi.govoet.my.id/?ss=eleven1",
        "label": "CH-5"
      },
      {
        "url": "https://multi.govoet.my.id/?ss=br3",
        "label": "CH-6"
      },
      {
        "url": "https://multi.govoet.my.id/?shaka=ziggo2",
        "label": "CH-NL"
      },
      {
        "url": "https://multi.govoet.my.id/?shaka=hrt2",
        "label": "CH-HR"
      },
      {
        "url": "https://multi.govoet.my.id/?shaka=tnt4",
        "label": "CH-EN"
      }
    ]
  },
  {
    "id": "ChampionsLeague-BayerLeverkusen-PSV",
    "league": "Champions League",
    "team1": {
      "name": "Bayer Leverkusen"
    },
    "team2": {
      "name": "PSV"
    },
    "kickoff_date": "2025-10-02",
    "kickoff_time": "02:00",
    "match_date": "2025-10-02",
    "match_time": "01:50",
    "duration": "3.5",
    "servers": [
      {
        "url": "https://multi.govoet.my.id/?envivo=37",
        "label": "CH-FR"
      },
      {
        "url": "https://multi.govoet.my.id/?envivo=168",
        "label": "CH-ES"
      },
      {
        "url": "https://multi.govoet.my.id/?envivo=115",
        "label": "CH-ES"
      },
      {
        "url": "https://multi.govoet.my.id/?envivo=111",
        "label": "CH-NL"
      },
      {
        "url": "https://multi.govoet.my.id/?envivo=93",
        "label": "CH-ES"
      },
      {
        "url": "https://multi.govoet.my.id/?ss=hd10",
        "label": "CH-1"
      }
    ]
  },
  {
    "id": "ChampionsLeague-Dortmund-AthBilbao",
    "league": "Champions League",
    "team1": {
      "name": "Dortmund"
    },
    "team2": {
      "name": "Ath Bilbao"
    },
    "kickoff_date": "2025-10-02",
    "kickoff_time": "02:00",
    "match_date": "2025-10-02",
    "match_time": "01:50",
    "duration": "3.5",
    "servers": [
      {
        "url": "https://multi.govoet.my.id/?envivo=35",
        "label": "CH-FR"
      },
      {
        "url": "https://multi.govoet.my.id/?envivo=162",
        "label": "CH-ES"
      },
      {
        "url": "https://multi.govoet.my.id/?envivo=123",
        "label": "CH-DE"
      },
      {
        "url": "https://multi.govoet.my.id/?envivo=92",
        "label": "CH-ES"
      },
      {
        "url": "https://multi.govoet.my.id/?ss=hd3",
        "label": "CH-1"
      },
      {
        "url": "https://multi.govoet.my.id/?ss=br1",
        "label": "CH-2"
      }
    ]
  },
  {
    "id": "ChampionsLeague-Monaco-ManchesterCity",
    "league": "Champions League",
    "team1": {
      "name": "Monaco"
    },
    "team2": {
      "name": "Manchester City"
    },
    "kickoff_date": "2025-10-02",
    "kickoff_time": "02:00",
    "match_date": "2025-10-02",
    "match_time": "01:50",
    "duration": "3.5",
    "servers": [
      {
        "url": "https://multi.govoet.my.id/?envivo=12",
        "label": "CH-FR"
      },
      {
        "url": "https://multi.govoet.my.id/?envivo=165",
        "label": "CH-ES"
      },
      {
        "url": "https://multi.govoet.my.id/?envivo=129",
        "label": "CH-GB"
      },
      {
        "url": "https://multi.govoet.my.id/?envivo=88",
        "label": "CH-ES"
      },
      {
        "url": "https://multi.govoet.my.id/?envivo=68",
        "label": "CH-ES"
      },
      {
        "url": "https://multi.govoet.my.id/?ss=hd2",
        "label": "CH-1"
      },
      {
        "url": "https://multi.govoet.my.id/?ss=eleven3",
        "label": "CH-2"
      },
      {
        "url": "https://multi.govoet.my.id/?ss=br4",
        "label": "CH-3"
      },
      {
        "url": "https://multi.govoet.my.id/?shaka=tnt2",
        "label": "CH-EN"
      },
      {
        "url": "https://multi.govoet.my.id/?shaka=ziggo5",
        "label": "CH-NL"
      }
    ]
  },
  {
    "id": "ChampionsLeague-Napoli-SportingCP",
    "league": "Champions League",
    "team1": {
      "name": "Napoli"
    },
    "team2": {
      "name": "Sporting CP"
    },
    "kickoff_date": "2025-10-02",
    "kickoff_time": "02:00",
    "match_date": "2025-10-02",
    "match_time": "01:50",
    "duration": "3.5",
    "servers": [
      {
        "url": "https://multi.govoet.my.id/?envivo=36",
        "label": "CH-FR"
      },
      {
        "url": "https://multi.govoet.my.id/?envivo=167",
        "label": "CH-ES"
      },
      {
        "url": "https://multi.govoet.my.id/?envivo=139",
        "label": "CH-IT"
      },
      {
        "url": "https://multi.govoet.my.id/?envivo=144",
        "label": "CH-PT"
      },
      {
        "url": "https://multi.govoet.my.id/?envivo=90",
        "label": "CH-ES"
      },
      {
        "url": "https://multi.govoet.my.id/?ss=hd8",
        "label": "CH-1"
      },
      {
        "url": "https://multi.govoet.my.id/?ss=sporttv5",
        "label": "CH-2"
      }
    ]
  },
  {
    "id": "ChampionsLeague-Villarreal-Juventus",
    "league": "Champions League",
    "team1": {
      "name": "Villarreal"
    },
    "team2": {
      "name": "Juventus"
    },
    "kickoff_date": "2025-10-02",
    "kickoff_time": "02:00",
    "match_date": "2025-10-02",
    "match_time": "01:50",
    "duration": "3.5",
    "servers": [
      {
        "url": "https://multi.govoet.my.id/?envivo=34",
        "label": "CH-FR"
      },
      {
        "url": "https://multi.govoet.my.id/?envivo=163",
        "label": "CH-ES"
      },
      {
        "url": "https://multi.govoet.my.id/?envivo=137",
        "label": "CH-IT"
      },
      {
        "url": "https://multi.govoet.my.id/?envivo=89",
        "label": "CH-ES"
      },
      {
        "url": "https://multi.govoet.my.id/?envivo=155",
        "label": "CH-ES"
      },
      {
        "url": "https://multi.govoet.my.id/?ss=hd11",
        "label": "CH-1"
      },
      {
        "url": "https://multi.govoet.my.id/?ss=hd7",
        "label": "CH-2"
      },
      {
        "url": "https://multi.govoet.my.id/?ss=br5",
        "label": "CH-3"
      }
    ]
  },
  {
    "id": "LigueDesChampions-Qarabag-FCCopenhague",
    "league": "Champions League",
    "team1": {
      "name": "Qarabag"
    },
    "team2": {
      "name": "FC Copenhague"
    },
    "kickoff_date": "2025-10-01",
    "kickoff_time": "23:45",
    "match_date": "2025-10-01",
    "match_time": "23:35",
    "duration": "3.5",
    "servers": [
      {
        "url": "https://multi.govoet.my.id/?envivo=13",
        "label": "CH-FR"
      },
      {
        "url": "https://multi.govoet.my.id/?envivo=163",
        "label": "CH-ES"
      },
      {
        "url": "https://multi.govoet.my.id/?envivo=130",
        "label": "CH-GB"
      },
      {
        "url": "https://multi.govoet.my.id/?envivo=88",
        "label": "CH-ES"
      },
      {
        "url": "https://multi.govoet.my.id/?iframe=aHR0cHM6Ly9zcG9ydC5pbnBsYXluZXQudGVjaC9saXZlc3RyZWFtLmh0bWw/c3JjPWFIUjBjSE02THk5emJXUXVjM0J2Y25Sd2JHRjVaWEl1YVc4dlpXMWlaV1F1Y0dod0x6OXRZWFJqYUY5cFpEMHhNekk1T0RJNE9DWnphejB4WXpsaFl6QXhKblI1Y0dVOWN5WndZWEpsYm5ROVpHVnRieTVwYm5Cc1lYbHVaWFF1WTI5dA==",
        "label": "CH-NA"
      },
      {
        "url": "https://multi.govoet.my.id/?ss=hd5",
        "label": "CH-1"
      },
      {
        "url": "https://multi.govoet.my.id/?ss=eleven2",
        "label": "CH-2"
      },
      {
        "url": "https://multi.govoet.my.id/?ss=br4",
        "label": "CH-3"
      }
    ]
  },
  {
    "id": "LigueDesChampions-RoyaleUnionSG-Newcastle",
    "league": "Champions League",
    "team1": {
      "name": "Royale Union SG"
    },
    "team2": {
      "name": "Newcastle"
    },
    "kickoff_date": "2025-10-01",
    "kickoff_time": "23:45",
    "match_date": "2025-10-01",
    "match_time": "23:35",
    "duration": "3.5",
    "servers": [
      {
        "url": "https://multi.govoet.my.id/?envivo=12",
        "label": "CH-FR"
      },
      {
        "url": "https://multi.govoet.my.id/?envivo=162",
        "label": "CH-ES"
      },
      {
        "url": "https://multi.govoet.my.id/?envivo=129",
        "label": "CH-GB"
      },
      {
        "url": "https://multi.govoet.my.id/?envivo=138",
        "label": "CH-IT"
      },
      {
        "url": "https://multi.govoet.my.id/?envivo=87",
        "label": "CH-ES"
      },
      {
        "url": "https://multi.govoet.my.id/?envivo=155",
        "label": "CH-ES"
      },
      {
        "url": "https://multi.govoet.my.id/?envivo=68",
        "label": "CH-ES"
      },
      {
        "url": "https://multi.govoet.my.id/?iframe=aHR0cHM6Ly9zcG9ydC5pbnBsYXluZXQudGVjaC9saXZlc3RyZWFtLmh0bWw/c3JjPWFIUjBjSE02THk5emJXUXVjM0J2Y25Sd2JHRjVaWEl1YVc4dlpXMWlaV1F1Y0dod0x6OXRZWFJqYUY5cFpEMHhNekk1T0RJNE9TWnphejB4WXpsaFl6QXhKblI1Y0dVOWN5WndZWEpsYm5ROVpHVnRieTVwYm5Cc1lYbHVaWFF1WTI5dA==",
        "label": "CH-NA"
      }
    ]
  },
  {
    "id": "EuroLeague-Monaco-ZalgirisKaunas",
    "league": "EuroLeague",
    "team1": {
      "name": "Monaco"
    },
    "team2": {
      "name": "Zalgiris Kaunas"
    },
    "kickoff_date": "2025-10-02",
    "kickoff_time": "00:30",
    "match_date": "2025-10-02",
    "match_time": "00:20",
    "duration": "3.5",
    "servers": [
      {
        "url": "https://multi.govoet.my.id/?envivo=64",
        "label": "CH-ES"
      }
    ]
  },
  {
    "id": "EuroLeague-Fenerbahce-Paris",
    "league": "EuroLeague",
    "team1": {
      "name": "Fenerbahce"
    },
    "team2": {
      "name": "Paris FC"
    },
    "kickoff_date": "2025-10-02",
    "kickoff_time": "00:45",
    "match_date": "2025-10-02",
    "match_time": "00:35",
    "duration": "3.5",
    "servers": [
      {
        "url": "https://multi.govoet.my.id/?envivo=63",
        "label": "CH-ES"
      }
    ]
  },
  {
    "id": "EuroLeague-Lyon-Villeurbanne-Valence",
    "league": "EuroLeague",
    "team1": {
      "name": "Lyon-Villeurbanne"
    },
    "team2": {
      "name": "Valencia"
    },
    "kickoff_date": "2025-10-02",
    "kickoff_time": "01:00",
    "match_date": "2025-10-02",
    "match_time": "00:50",
    "duration": "3.5",
    "servers": [
      {
        "url": "https://multi.govoet.my.id/?envivo=55",
        "label": "CH-ES"
      }
    ]
  },
  {
    "id": "Championship-Millwall-Coventry",
    "league": "Championship",
    "team1": {
      "name": "Millwall"
    },
    "team2": {
      "name": "Coventry"
    },
    "kickoff_date": "2025-10-02",
    "kickoff_time": "01:45",
    "match_date": "2025-10-02",
    "match_time": "01:35",
    "duration": "3.5",
    "servers": [
      {
        "url": "https://multi.govoet.my.id/?envivo=170",
        "label": "CH-US"
      }
    ]
  },
  {
    "id": "Championship-Norwich-WestBrom",
    "league": "Championship",
    "team1": {
      "name": "Norwich"
    },
    "team2": {
      "name": "West Brom"
    },
    "kickoff_date": "2025-10-02",
    "kickoff_time": "01:45",
    "match_date": "2025-10-02",
    "match_time": "01:35",
    "duration": "3.5",
    "servers": [
      {
        "url": "https://multi.govoet.my.id/?envivo=171",
        "label": "CH-US"
      }
    ]
  },
  {
    "id": "Championship-Portsmouth-Watford",
    "league": "Championship",
    "team1": {
      "name": "Portsmouth"
    },
    "team2": {
      "name": "Watford"
    },
    "kickoff_date": "2025-10-02",
    "kickoff_time": "01:45",
    "match_date": "2025-10-02",
    "match_time": "01:35",
    "duration": "3.5",
    "servers": [
      {
        "url": "https://multi.govoet.my.id/?envivo=172",
        "label": "CH-US"
      }
    ]
  },
  {
    "id": "Championship-QPR-OxfordUtd",
    "league": "Championship",
    "team1": {
      "name": "QPR"
    },
    "team2": {
      "name": "Oxford Utd"
    },
    "kickoff_date": "2025-10-02",
    "kickoff_time": "02:00",
    "match_date": "2025-10-02",
    "match_time": "01:50",
    "duration": "3.5",
    "servers": [
      {
        "url": "https://multi.govoet.my.id/?envivo=4",
        "label": "CH-FR"
      },
      {
        "url": "https://multi.govoet.my.id/?envivo=173",
        "label": "CH-US"
      },
      {
        "url": "https://multi.govoet.my.id/?envivo=100",
        "label": "CH-ES"
      }
    ]
  },
  {
    "id": "LigueDesChampions-MultiplexLiguedesChampions",
    "league": "Champions League",
    "team1": {
      "name": "Multiplex Ligue des Champions"
    },
    "team2": {
      "name": ""
    },
    "kickoff_date": "2025-10-02",
    "kickoff_time": "02:00",
    "match_date": "2025-10-02",
    "match_time": "01:50",
    "duration": "3.5",
    "servers": [
      {
        "url": "https://multi.govoet.my.id/?envivo=14",
        "label": "CH-FR"
      },
      {
        "url": "https://multi.govoet.my.id/?envivo=164",
        "label": "CH-ES"
      },
      {
        "url": "https://multi.govoet.my.id/?envivo=124",
        "label": "CH-DE"
      }
    ]
  },
  {
    "id": "CoupeDuMondeU20-Espagne-Mexique",
    "league": "Coupe Du Monde U20",
    "team1": {
      "name": "Spain"
    },
    "team2": {
      "name": "Mexico"
    },
    "kickoff_date": "2025-10-02",
    "kickoff_time": "03:00",
    "match_date": "2025-10-02",
    "match_time": "02:50",
    "duration": "3.5",
    "servers": [
      {
        "url": "https://multi.govoet.my.id/?envivo=61",
        "label": "CH-ES"
      },
      {
        "url": "https://multi.govoet.my.id/?envivo=96",
        "label": "CH-ES"
      }
    ]
  },
  {
    "id": "CoupeDuMondeU20-Italie-Curaçao",
    "league": "Coupe Du Monde U20",
    "team1": {
      "name": "Italy"
    },
    "team2": {
      "name": "Curacao"
    },
    "kickoff_date": "2025-10-02",
    "kickoff_time": "03:00",
    "match_date": "2025-10-02",
    "match_time": "02:50",
    "duration": "3.5",
    "servers": [
      {
        "url": "https://multi.govoet.my.id/?envivo=95",
        "label": "CH-ES"
      }
    ]
  },
  {
    "id": "CoupeDuMondeU20-Argentine-Australie",
    "league": "Coupe Du Monde U20",
    "team1": {
      "name": "Argentina"
    },
    "team2": {
      "name": "Australie"
    },
    "kickoff_date": "2025-10-02",
    "kickoff_time": "06:00",
    "match_date": "2025-10-02",
    "match_time": "05:50",
    "duration": "3.5",
    "servers": [
      {
        "url": "https://multi.govoet.my.id/?envivo=64",
        "label": "CH-ES"
      }
    ]
  },
  {
    "id": "CoupeDuMondeU20-Brésil-Maroc",
    "league": "Coupe Du Monde U20",
    "team1": {
      "name": "Brazil"
    },
    "team2": {
      "name": "Morocco"
    },
    "kickoff_date": "2025-10-02",
    "kickoff_time": "06:00",
    "match_date": "2025-10-02",
    "match_time": "05:50",
    "duration": "3.5",
    "servers": [
      {
        "url": "https://multi.govoet.my.id/?envivo=96",
        "label": "CH-ES"
      }
    ]
  },
  {
    "id": "Liga1TeApuesto-AlianzaAtl.-U.deDeportes",
    "league": "Liga 1 Te Apuesto",
    "team1": {
      "name": "Alianza Atl."
    },
    "team2": {
      "name": "U. de Deportes"
    },
    "kickoff_date": "2025-10-02",
    "kickoff_time": "06:00",
    "match_date": "2025-10-02",
    "match_time": "05:50",
    "duration": "3.5",
    "servers": [
      {
        "url": "https://multi.govoet.my.id/?envivo=84",
        "label": "CH-ES"
      },
      {
        "url": "https://multi.govoet.my.id/?envivo=70",
        "label": "CH-ES"
      }
    ]
  },
  {
    "id": "CopaEcuador-LDUPortoviejo-U.Catolica",
    "league": "Copa Ecuador",
    "team1": {
      "name": "LDU Portoviejo"
    },
    "team2": {
      "name": "U. Catolica"
    },
    "kickoff_date": "2025-10-02",
    "kickoff_time": "07:00",
    "match_date": "2025-10-02",
    "match_time": "06:50",
    "duration": "3.5",
    "servers": [
      {
        "url": "https://multi.govoet.my.id/?envivo=86",
        "label": "CH-ES"
      }
    ]
  },
  {
    "id": "CopaColombia-SantaFe-Ind.Medellin",
    "league": "Copa Colombia",
    "team1": {
      "name": "Santa Fe"
    },
    "team2": {
      "name": "Ind. Medellin"
    },
    "kickoff_date": "2025-10-02",
    "kickoff_time": "08:00",
    "match_date": "2025-10-02",
    "match_time": "07:50",
    "duration": "3.5",
    "servers": [
      {
        "url": "https://multi.govoet.my.id/?envivo=82",
        "label": "CH-ES"
      }
    ]
  },
  {
    "id": "Liga1TeApuesto-A.Lima-Grau",
    "league": "Liga 1 Te Apuesto",
    "team1": {
      "name": "A. Lima"
    },
    "team2": {
      "name": "Grau"
    },
    "kickoff_date": "2025-10-02",
    "kickoff_time": "08:30",
    "match_date": "2025-10-02",
    "match_time": "08:20",
    "duration": "3.5",
    "servers": [
      {
        "url": "https://multi.govoet.my.id/?envivo=84",
        "label": "CH-ES"
      },
      {
        "url": "https://multi.govoet.my.id/?envivo=70",
        "label": "CH-ES"
      }
    ]
  },
  {
    "id": "48854611",
    "league": "Germany - 3. Liga",
    "team1": {
      "name": "SSV Ulm 1846"
    },
    "team2": {
      "name": "1. FC Schweinfurt 05"
    },
    "kickoff_date": "live",
    "kickoff_time": "live",
    "match_date": "live",
    "match_time": "live",
    "duration": "live",
    "servers": [
      {
        "url": "https://multi.govoet.my.id/?iframe=aHR0cHM6Ly9zcG9ydC5pbnBsYXluZXQudGVjaC9saXZlc3RyZWFtLmh0bWw/c3JjPWFIUjBjSE02THk5emJXUXVjM0J2Y25Sd2JHRjVaWEl1YVc4dlpXMWlaV1F1Y0dod0x6OXRZWFJqYUY5cFpEMHhNek15TmpJeE9TWnphejB4WXpsaFl6QXhKblI1Y0dVOWN5WndZWEpsYm5ROVpHVnRieTVwYm5Cc1lYbHVaWFF1WTI5dA==",
        "label": "CH-NA"
      }
    ]
  },
  {
    "id": "48854612",
    "league": "Germany - 3. Liga",
    "team1": {
      "name": "Rot-Weiss Essen"
    },
    "team2": {
      "name": "1899 Hoffenheim II"
    },
    "kickoff_date": "live",
    "kickoff_time": "live",
    "match_date": "live",
    "match_time": "live",
    "duration": "live",
    "servers": [
      {
        "url": "https://multi.govoet.my.id/?iframe=aHR0cHM6Ly9zcG9ydC5pbnBsYXluZXQudGVjaC9saXZlc3RyZWFtLmh0bWw/c3JjPWFIUjBjSE02THk5emJXUXVjM0J2Y25Sd2JHRjVaWEl1YVc4dlpXMWlaV1F1Y0dod0x6OXRZWFJqYUY5cFpEMHhNek15TmpJeU1DWnphejB4WXpsaFl6QXhKblI1Y0dVOWN5WndZWEpsYm5ROVpHVnRieTVwYm5Cc1lYbHVaWFF1WTI5dA==",
        "label": "CH-NA"
      }
    ]
  },
  {
    "id": "48854628",
    "league": "Germany - 3. Liga",
    "team1": {
      "name": "Verl"
    },
    "team2": {
      "name": "Ingolstadt"
    },
    "kickoff_date": "live",
    "kickoff_time": "live",
    "match_date": "live",
    "match_time": "live",
    "duration": "live",
    "servers": [
      {
        "url": "https://multi.govoet.my.id/?iframe=aHR0cHM6Ly9zcG9ydC5pbnBsYXluZXQudGVjaC9saXZlc3RyZWFtLmh0bWw/c3JjPWFIUjBjSE02THk5emJXUXVjM0J2Y25Sd2JHRjVaWEl1YVc4dlpXMWlaV1F1Y0dod0x6OXRZWFJqYUY5cFpEMHhNek15TmpJeE5TWnphejB4WXpsaFl6QXhKblI1Y0dVOWN5WndZWEpsYm5ROVpHVnRieTVwYm5Cc1lYbHVaWFF1WTI5dA==",
        "label": "CH-NA"
      }
    ]
  },
  {
    "id": "48854627",
    "league": "Germany - 3. Liga",
    "team1": {
      "name": "Munich1860"
    },
    "team2": {
      "name": "Viktoria Cologne"
    },
    "kickoff_date": "live",
    "kickoff_time": "live",
    "match_date": "live",
    "match_time": "live",
    "duration": "live",
    "servers": [
      {
        "url": "https://multi.govoet.my.id/?iframe=aHR0cHM6Ly9zcG9ydC5pbnBsYXluZXQudGVjaC9saXZlc3RyZWFtLmh0bWw/c3JjPWFIUjBjSE02THk5emJXUXVjM0J2Y25Sd2JHRjVaWEl1YVc4dlpXMWlaV1F1Y0dod0x6OXRZWFJqYUY5cFpEMHhNek15TmpJeE55WnphejB4WXpsaFl6QXhKblI1Y0dVOWN5WndZWEpsYm5ROVpHVnRieTVwYm5Cc1lYbHVaWFF1WTI5dA==",
        "label": "CH-NA"
      }
    ]
  },
  {
    "id": "48854613",
    "league": "Germany - 3. Liga",
    "team1": {
      "name": "VfL 1899 Osnabruck"
    },
    "team2": {
      "name": "Regensburg"
    },
    "kickoff_date": "live",
    "kickoff_time": "live",
    "match_date": "live",
    "match_time": "live",
    "duration": "live",
    "servers": [
      {
        "url": "https://multi.govoet.my.id/?iframe=aHR0cHM6Ly9zcG9ydC5pbnBsYXluZXQudGVjaC9saXZlc3RyZWFtLmh0bWw/c3JjPWFIUjBjSE02THk5emJXUXVjM0J2Y25Sd2JHRjVaWEl1YVc4dlpXMWlaV1F1Y0dod0x6OXRZWFJqYUY5cFpEMHhNek15TmpJeE9DWnphejB4WXpsaFl6QXhKblI1Y0dVOWN5WndZWEpsYm5ROVpHVnRieTVwYm5Cc1lYbHVaWFF1WTI5dA==",
        "label": "CH-NA"
      }
    ]
  },
  {
    "id": "54428449",
    "league": "Spain - Copa de SM La Reina",
    "team1": {
      "name": "CDE Racing W."
    },
    "team2": {
      "name": "Alaves W."
    },
    "kickoff_date": "live",
    "kickoff_time": "live",
    "match_date": "live",
    "match_time": "live",
    "duration": "live",
    "servers": [
      {
        "url": "https://multi.govoet.my.id/?iframe=aHR0cHM6Ly9zcG9ydC5pbnBsYXluZXQudGVjaC9saXZlc3RyZWFtLmh0bWw/c3JjPWFIUjBjSE02THk5emJXUXVjM0J2Y25Sd2JHRjVaWEl1YVc4dlpXMWlaV1F1Y0dod0x6OXRZWFJqYUY5cFpEMHhNek16TXpjNU1DWnphejB4WXpsaFl6QXhKblI1Y0dVOWN5WndZWEpsYm5ROVpHVnRieTVwYm5Cc1lYbHVaWFF1WTI5dA==",
        "label": "CH-NA"
      }
    ]
  },
  {
    "id": "51387544",
    "league": "International Clubs - AFC Cup, Group Stage",
    "team1": {
      "name": "AL Wehdat Jor"
    },
    "team2": {
      "name": "Al-Wasl FC"
    },
    "kickoff_date": "live",
    "kickoff_time": "live",
    "match_date": "live",
    "match_time": "live",
    "duration": "live",
    "servers": [
      {
        "url": "https://multi.govoet.my.id/?iframe=aHR0cHM6Ly9zcG9ydC5pbnBsYXluZXQudGVjaC9saXZlc3RyZWFtLmh0bWw/c3JjPWFIUjBjSE02THk5emJXUXVjM0J2Y25Sd2JHRjVaWEl1YVc4dlpXMWlaV1F1Y0dod0x6OXRZWFJqYUY5cFpEMHhNek15TmpJd01DWnphejB4WXpsaFl6QXhKblI1Y0dVOWN5WndZWEpsYm5ROVpHVnRieTVwYm5Cc1lYbHVaWFF1WTI5dA==",
        "label": "CH-NA"
      }
    ]
  },
  {
    "id": "54142477",
    "league": "International Youth - UEFA Youth League, Knockout stage",
    "team1": {
      "name": "Dinamo Tbilisi"
    },
    "team2": {
      "name": "Zrinjski Mostar U19"
    },
    "kickoff_date": "live",
    "kickoff_time": "live",
    "match_date": "live",
    "match_time": "live",
    "duration": "live",
    "servers": [
      {
        "url": "https://multi.govoet.my.id/?iframe=aHR0cHM6Ly9zcG9ydC5pbnBsYXluZXQudGVjaC9saXZlc3RyZWFtLmh0bWw/c3JjPWFIUjBjSE02THk5emJXUXVjM0J2Y25Sd2JHRjVaWEl1YVc4dlpXMWlaV1F1Y0dod0x6OXRZWFJqYUY5cFpEMHhNek15TmpJek55WnphejB4WXpsaFl6QXhKblI1Y0dVOWN5WndZWEpsYm5ROVpHVnRieTVwYm5Cc1lYbHVaWFF1WTI5dA==",
        "label": "CH-NA"
      }
    ]
  },
  {
    "id": "51387542",
    "league": "International Clubs - AFC Cup, Group Stage",
    "team1": {
      "name": "Esteghlal Tehran"
    },
    "team2": {
      "name": "Al-Muharraq SC"
    },
    "kickoff_date": "live",
    "kickoff_time": "live",
    "match_date": "live",
    "match_time": "live",
    "duration": "live",
    "servers": [
      {
        "url": "https://multi.govoet.my.id/?iframe=aHR0cHM6Ly9zcG9ydC5pbnBsYXluZXQudGVjaC9saXZlc3RyZWFtLmh0bWw/c3JjPWFIUjBjSE02THk5emJXUXVjM0J2Y25Sd2JHRjVaWEl1YVc4dlpXMWlaV1F1Y0dod0x6OXRZWFJqYUY5cFpEMHhNek15TmpJd01TWnphejB4WXpsaFl6QXhKblI1Y0dVOWN5WndZWEpsYm5ROVpHVnRieTVwYm5Cc1lYbHVaWFF1WTI5dA==",
        "label": "CH-NA"
      }
    ]
  },
  {
    "id": "54247926",
    "league": "Switzerland - Promotion League",
    "team1": {
      "name": "SC Kriens"
    },
    "team2": {
      "name": "Breitenrain"
    },
    "kickoff_date": "live",
    "kickoff_time": "live",
    "match_date": "live",
    "match_time": "live",
    "duration": "live",
    "servers": [
      {
        "url": "https://multi.govoet.my.id/?iframe=aHR0cHM6Ly9zcG9ydC5pbnBsYXluZXQudGVjaC9saXZlc3RyZWFtLmh0bWw/c3JjPWFIUjBjSE02THk5emJXUXVjM0J2Y25Sd2JHRjVaWEl1YVc4dlpXMWlaV1F1Y0dod0x6OXRZWFJqYUY5cFpEMHhNek16TkRBM09DWnphejB4WXpsaFl6QXhKblI1Y0dVOWN5WndZWEpsYm5ROVpHVnRieTVwYm5Cc1lYbHVaWFF1WTI5dA==",
        "label": "CH-NA"
      }
    ]
  },
  {
    "id": "53629533",
    "league": "Sweden - Damallsvenskan, Women",
    "team1": {
      "name": "Malmo FF"
    },
    "team2": {
      "name": "Hacken Gothenburg W."
    },
    "kickoff_date": "live",
    "kickoff_time": "live",
    "match_date": "live",
    "match_time": "live",
    "duration": "live",
    "servers": [
      {
        "url": "https://multi.govoet.my.id/?iframe=aHR0cHM6Ly9zcG9ydC5pbnBsYXluZXQudGVjaC9saXZlc3RyZWFtLmh0bWw/c3JjPWFIUjBjSE02THk5emJXUXVjM0J2Y25Sd2JHRjVaWEl1YVc4dlpXMWlaV1F1Y0dod0x6OXRZWFJqYUY5cFpEMHhNek15TmpRMk9DWnphejB4WXpsaFl6QXhKblI1Y0dVOWN5WndZWEpsYm5ROVpHVnRieTVwYm5Cc1lYbHVaWFF1WTI5dA==",
        "label": "CH-NA"
      }
    ]
  },
  {
    "id": "54051035",
    "league": "Czech Republic - 1. Liga",
    "team1": {
      "name": "Pardubice"
    },
    "team2": {
      "name": "FC Banik Ostrava"
    },
    "kickoff_date": "live",
    "kickoff_time": "live",
    "match_date": "live",
    "match_time": "live",
    "duration": "live",
    "servers": [
      {
        "url": "https://multi.govoet.my.id/?iframe=aHR0cHM6Ly9zcG9ydC5pbnBsYXluZXQudGVjaC9saXZlc3RyZWFtLmh0bWw/c3JjPWFIUjBjSE02THk5emJXUXVjM0J2Y25Sd2JHRjVaWEl1YVc4dlpXMWlaV1F1Y0dod0x6OXRZWFJqYUY5cFpEMHhNekk1T0RRd09TWnphejB4WXpsaFl6QXhKblI1Y0dVOWN5WndZWEpsYm5ROVpHVnRieTVwYm5Cc1lYbHVaWFF1WTI5dA==",
        "label": "CH-NA"
      }
    ]
  },
  {
    "id": "51455588",
    "league": "Norway - Eliteserien",
    "team1": {
      "name": "KFUM Oslo"
    },
    "team2": {
      "name": "Fredrikstad"
    },
    "kickoff_date": "live",
    "kickoff_time": "live",
    "match_date": "live",
    "match_time": "live",
    "duration": "live",
    "servers": [
      {
        "url": "https://multi.govoet.my.id/?iframe=aHR0cHM6Ly9zcG9ydC5pbnBsYXluZXQudGVjaC9saXZlc3RyZWFtLmh0bWw/c3JjPWFIUjBjSE02THk5emJXUXVjM0J2Y25Sd2JHRjVaWEl1YVc4dlpXMWlaV1F1Y0dod0x6OXRZWFJqYUY5cFpEMHhNekk1T0RRd05TWnphejB4WXpsaFl6QXhKblI1Y0dVOWN5WndZWEpsYm5ROVpHVnRieTVwYm5Cc1lYbHVaWFF1WTI5dA==",
        "label": "CH-NA"
      }
    ]
  },
  {
    "id": "52649055",
    "league": "Slovakia - Superliga",
    "team1": {
      "name": "FK Kosice"
    },
    "team2": {
      "name": "Dac Dunajska Streda"
    },
    "kickoff_date": "live",
    "kickoff_time": "live",
    "match_date": "live",
    "match_time": "live",
    "duration": "live",
    "servers": [
      {
        "url": "https://multi.govoet.my.id/?iframe=aHR0cHM6Ly9zcG9ydC5pbnBsYXluZXQudGVjaC9saXZlc3RyZWFtLmh0bWw/c3JjPWFIUjBjSE02THk5emJXUXVjM0J2Y25Sd2JHRjVaWEl1YVc4dlpXMWlaV1F1Y0dod0x6OXRZWFJqYUY5cFpEMHhNekk1T0RRd05pWnphejB4WXpsaFl6QXhKblI1Y0dVOWN5WndZWEpsYm5ROVpHVnRieTVwYm5Cc1lYbHVaWFF1WTI5dA==",
        "label": "CH-NA"
      }
    ]
  },
  {
    "id": "53928471",
    "league": "USA - USL, League One",
    "team1": {
      "name": "Union Omaha SC"
    },
    "team2": {
      "name": "Portland Hearts of Pine"
    },
    "kickoff_date": "live",
    "kickoff_time": "live",
    "match_date": "live",
    "match_time": "live",
    "duration": "live",
    "servers": [
      {
        "url": "https://multi.govoet.my.id/?iframe=aHR0cHM6Ly9zcG9ydC5pbnBsYXluZXQudGVjaC9saXZlc3RyZWFtLmh0bWw/c3JjPWFIUjBjSE02THk5emJXUXVjM0J2Y25Sd2JHRjVaWEl1YVc4dlpXMWlaV1F1Y0dod0x6OXRZWFJqYUY5cFpEMHhNek15TmpRMU5TWnphejB4WXpsaFl6QXhKblI1Y0dVOWN5WndZWEpsYm5ROVpHVnRieTVwYm5Cc1lYbHVaWFF1WTI5dA==",
        "label": "CH-NA"
      }
    ]
  },
  {
    "id": "54209097",
    "league": "Lithuania - A Lyga",
    "team1": {
      "name": "Panevezys"
    },
    "team2": {
      "name": "Alytus Dfk Dainava"
    },
    "kickoff_date": "live",
    "kickoff_time": "live",
    "match_date": "live",
    "match_time": "live",
    "duration": "live",
    "servers": [
      {
        "url": "https://multi.govoet.my.id/?iframe=aHR0cHM6Ly9zcG9ydC5pbnBsYXluZXQudGVjaC9saXZlc3RyZWFtLmh0bWw/c3JjPWFIUjBjSE02THk5emJXUXVjM0J2Y25Sd2JHRjVaWEl1YVc4dlpXMWlaV1F1Y0dod0x6OXRZWFJqYUY5cFpEMHhNek15TmpJMU9DWnphejB4WXpsaFl6QXhKblI1Y0dVOWN5WndZWEpsYm5ROVpHVnRieTVwYm5Cc1lYbHVaWFF1WTI5dA==",
        "label": "CH-NA"
      }
    ]
  },
  {
    "id": "54126815",
    "league": "Morocco - Botola",
    "team1": {
      "name": "Far Rabat"
    },
    "team2": {
      "name": "Ittihad Tanger"
    },
    "kickoff_date": "live",
    "kickoff_time": "live",
    "match_date": "live",
    "match_time": "live",
    "duration": "live",
    "servers": [
      {
        "url": "https://multi.govoet.my.id/?iframe=aHR0cHM6Ly9zcG9ydC5pbnBsYXluZXQudGVjaC9saXZlc3RyZWFtLmh0bWw/c3JjPWFIUjBjSE02THk5emJXUXVjM0J2Y25Sd2JHRjVaWEl1YVc4dlpXMWlaV1F1Y0dod0x6OXRZWFJqYUY5cFpEMHhNek15TmpJMk15WnphejB4WXpsaFl6QXhKblI1Y0dVOWN5WndZWEpsYm5ROVpHVnRieTVwYm5Cc1lYbHVaWFF1WTI5dA==",
        "label": "CH-NA"
      }
    ]
  },
  {
    "id": "54247970",
    "league": "Lithuania - A Lyga",
    "team1": {
      "name": "Hegelmann Kaunas"
    },
    "team2": {
      "name": "Kauno Zalgiris"
    },
    "kickoff_date": "live",
    "kickoff_time": "live",
    "match_date": "live",
    "match_time": "live",
    "duration": "live",
    "servers": [
      {
        "url": "https://multi.govoet.my.id/?iframe=aHR0cHM6Ly9zcG9ydC5pbnBsYXluZXQudGVjaC9saXZlc3RyZWFtLmh0bWw/c3JjPWFIUjBjSE02THk5emJXUXVjM0J2Y25Sd2JHRjVaWEl1YVc4dlpXMWlaV1F1Y0dod0x6OXRZWFJqYUY5cFpEMHhNek15TmpJMU9TWnphejB4WXpsaFl6QXhKblI1Y0dVOWN5WndZWEpsYm5ROVpHVnRieTVwYm5Cc1lYbHVaWFF1WTI5dA==",
        "label": "CH-NA"
      }
    ]
  },
  {
    "id": "54265893",
    "league": "South Africa - Premiership",
    "team1": {
      "name": "Kaizer Chiefs"
    },
    "team2": {
      "name": "Amazulu"
    },
    "kickoff_date": "live",
    "kickoff_time": "live",
    "match_date": "live",
    "match_time": "live",
    "duration": "live",
    "servers": [
      {
        "url": "https://multi.govoet.my.id/?iframe=aHR0cHM6Ly9zcG9ydC5pbnBsYXluZXQudGVjaC9saXZlc3RyZWFtLmh0bWw/c3JjPWFIUjBjSE02THk5emJXUXVjM0J2Y25Sd2JHRjVaWEl1YVc4dlpXMWlaV1F1Y0dod0x6OXRZWFJqYUY5cFpEMHhNek15TmpRM01TWnphejB4WXpsaFl6QXhKblI1Y0dVOWN5WndZWEpsYm5ROVpHVnRieTVwYm5Cc1lYbHVaWFF1WTI5dA==",
        "label": "CH-NA"
      }
    ]
  },
  {
    "id": "51729635",
    "league": "Russia - Russian Cup, Group 4",
    "team1": {
      "name": "FK Baltika Kaliningrad"
    },
    "team2": {
      "name": "Akron Tolyatti"
    },
    "kickoff_date": "live",
    "kickoff_time": "live",
    "match_date": "live",
    "match_time": "live",
    "duration": "live",
    "servers": [
      {
        "url": "https://multi.govoet.my.id/?iframe=aHR0cHM6Ly9zcG9ydC5pbnBsYXluZXQudGVjaC9saXZlc3RyZWFtLmh0bWw/c3JjPWFIUjBjSE02THk5emJXUXVjM0J2Y25Sd2JHRjVaWEl1YVc4dlpXMWlaV1F1Y0dod0x6OXRZWFJqYUY5cFpEMHhNek15TmpRd09DWnphejB4WXpsaFl6QXhKblI1Y0dVOWN5WndZWEpsYm5ROVpHVnRieTVwYm5Cc1lYbHVaWFF1WTI5dA==",
        "label": "CH-NA"
      }
    ]
  },
  {
    "id": "49375012",
    "league": "International - Euroleague",
    "team1": {
      "name": "AS Monaco"
    },
    "team2": {
      "name": "Zalgiris Kaunas"
    },
    "kickoff_date": "live",
    "kickoff_time": "live",
    "match_date": "live",
    "match_time": "live",
    "duration": "live",
    "servers": [
      {
        "url": "https://multi.govoet.my.id/?iframe=aHR0cHM6Ly9zcG9ydC5pbnBsYXluZXQudGVjaC9saXZlc3RyZWFtLmh0bWw/c3JjPWFIUjBjSE02THk5emJXUXVjM0J2Y25Sd2JHRjVaWEl1YVc4dlpXMWlaV1F1Y0dod0x6OXRZWFJqYUY5cFpEMHhNek14T0RRMk1pWnphejB4WXpsaFl6QXhKblI1Y0dVOWN5WndZWEpsYm5ROVpHVnRieTVwYm5Cc1lYbHVaWFF1WTI5dA==",
        "label": "CH-NA"
      }
    ]
  },
  {
    "id": "51729637",
    "league": "Russia - Russian Cup, Group 4",
    "team1": {
      "name": "Lokomotiv Moscow"
    },
    "team2": {
      "name": "CSKA Moscow"
    },
    "kickoff_date": "live",
    "kickoff_time": "live",
    "match_date": "live",
    "match_time": "live",
    "duration": "live",
    "servers": [
      {
        "url": "https://multi.govoet.my.id/?iframe=aHR0cHM6Ly9zcG9ydC5pbnBsYXluZXQudGVjaC9saXZlc3RyZWFtLmh0bWw/c3JjPWFIUjBjSE02THk5emJXUXVjM0J2Y25Sd2JHRjVaWEl1YVc4dlpXMWlaV1F1Y0dod0x6OXRZWFJqYUY5cFpEMHhNek15TmpReE9TWnphejB4WXpsaFl6QXhKblI1Y0dVOWN5WndZWEpsYm5ROVpHVnRieTVwYm5Cc1lYbHVaWFF1WTI5dA==",
        "label": "CH-NA"
      }
    ]
  },
  {
    "id": "49375017",
    "league": "International - Euroleague",
    "team1": {
      "name": "Fenerbahce"
    },
    "team2": {
      "name": "Paris Basketball"
    },
    "kickoff_date": "live",
    "kickoff_time": "live",
    "match_date": "live",
    "match_time": "live",
    "duration": "live",
    "servers": [
      {
        "url": "https://multi.govoet.my.id/?iframe=aHR0cHM6Ly9zcG9ydC5pbnBsYXluZXQudGVjaC9saXZlc3RyZWFtLmh0bWw/c3JjPWFIUjBjSE02THk5emJXUXVjM0J2Y25Sd2JHRjVaWEl1YVc4dlpXMWlaV1F1Y0dod0x6OXRZWFJqYUY5cFpEMHhNek14T0RRMk15WnphejB4WXpsaFl6QXhKblI1Y0dVOWN5WndZWEpsYm5ROVpHVnRieTVwYm5Cc1lYbHVaWFF1WTI5dA==",
        "label": "CH-NA"
      }
    ]
  },
  {
    "id": "51662350",
    "league": "International - EuroCup Group Stage",
    "team1": {
      "name": "Panionios BC"
    },
    "team2": {
      "name": "Niners Chemnitz"
    },
    "kickoff_date": "live",
    "kickoff_time": "live",
    "match_date": "live",
    "match_time": "live",
    "duration": "live",
    "servers": [
      {
        "url": "https://multi.govoet.my.id/?iframe=aHR0cHM6Ly9zcG9ydC5pbnBsYXluZXQudGVjaC9saXZlc3RyZWFtLmh0bWw/c3JjPWFIUjBjSE02THk5emJXUXVjM0J2Y25Sd2JHRjVaWEl1YVc4dlpXMWlaV1F1Y0dod0x6OXRZWFJqYUY5cFpEMHhNek15TnpRME5TWnphejB4WXpsaFl6QXhKblI1Y0dVOWN5WndZWEpsYm5ROVpHVnRieTVwYm5Cc1lYbHVaWFF1WTI5dA==",
        "label": "CH-NA"
      }
    ]
  },
  {
    "id": "54414149",
    "league": "International - EuroCup Group Stage",
    "team1": {
      "name": "Universitatea Cluj-Napoca"
    },
    "team2": {
      "name": "Bahcesehir Koleji"
    },
    "kickoff_date": "live",
    "kickoff_time": "live",
    "match_date": "live",
    "match_time": "live",
    "duration": "live",
    "servers": [
      {
        "url": "https://multi.govoet.my.id/?iframe=aHR0cHM6Ly9zcG9ydC5pbnBsYXluZXQudGVjaC9saXZlc3RyZWFtLmh0bWw/c3JjPWFIUjBjSE02THk5emJXUXVjM0J2Y25Sd2JHRjVaWEl1YVc4dlpXMWlaV1F1Y0dod0x6OXRZWFJqYUY5cFpEMHhNek14T0RRM05TWnphejB4WXpsaFl6QXhKblI1Y0dVOWN5WndZWEpsYm5ROVpHVnRieTVwYm5Cc1lYbHVaWFF1WTI5dA==",
        "label": "CH-NA"
      }
    ]
  },
  {
    "id": "54195995",
    "league": "International - EuroCup Group Stage",
    "team1": {
      "name": "BC Lietkabelis Panevezys"
    },
    "team2": {
      "name": "Besiktas JK"
    },
    "kickoff_date": "live",
    "kickoff_time": "live",
    "match_date": "live",
    "match_time": "live",
    "duration": "live",
    "servers": [
      {
        "url": "https://multi.govoet.my.id/?iframe=aHR0cHM6Ly9zcG9ydC5pbnBsYXluZXQudGVjaC9saXZlc3RyZWFtLmh0bWw/c3JjPWFIUjBjSE02THk5emJXUXVjM0J2Y25Sd2JHRjVaWEl1YVc4dlpXMWlaV1F1Y0dod0x6OXRZWFJqYUY5cFpEMHhNek14T0RRM05DWnphejB4WXpsaFl6QXhKblI1Y0dVOWN5WndZWEpsYm5ROVpHVnRieTVwYm5Cc1lYbHVaWFF1WTI5dA==",
        "label": "CH-NA"
      }
    ]
  },
  {
    "id": "51662349",
    "league": "International - EuroCup Group Stage",
    "team1": {
      "name": "Cedevita Olimpija Ljubljana"
    },
    "team2": {
      "name": "Manresa"
    },
    "kickoff_date": "live",
    "kickoff_time": "live",
    "match_date": "live",
    "match_time": "live",
    "duration": "live",
    "servers": [
      {
        "url": "https://multi.govoet.my.id/?iframe=aHR0cHM6Ly9zcG9ydC5pbnBsYXluZXQudGVjaC9saXZlc3RyZWFtLmh0bWw/c3JjPWFIUjBjSE02THk5emJXUXVjM0J2Y25Sd2JHRjVaWEl1YVc4dlpXMWlaV1F1Y0dod0x6OXRZWFJqYUY5cFpEMHhNek14T0RRM05pWnphejB4WXpsaFl6QXhKblI1Y0dVOWN5WndZWEpsYm5ROVpHVnRieTVwYm5Cc1lYbHVaWFF1WTI5dA==",
        "label": "CH-NA"
      }
    ]
  },
  {
    "id": "53491407",
    "league": "International - United League, Main Round",
    "team1": {
      "name": "Zenit St Petersburg"
    },
    "team2": {
      "name": "Avtodor Saratov"
    },
    "kickoff_date": "live",
    "kickoff_time": "live",
    "match_date": "live",
    "match_time": "live",
    "duration": "live",
    "servers": [
      {
        "url": "https://multi.govoet.my.id/?iframe=aHR0cHM6Ly9zcG9ydC5pbnBsYXluZXQudGVjaC9saXZlc3RyZWFtLmh0bWw/c3JjPWFIUjBjSE02THk5emJXUXVjM0J2Y25Sd2JHRjVaWEl1YVc4dlpXMWlaV1F1Y0dod0x6OXRZWFJqYUY5cFpEMHhNek15TmpRM055WnphejB4WXpsaFl6QXhKblI1Y0dVOWN5WndZWEpsYm5ROVpHVnRieTVwYm5Cc1lYbHVaWFF1WTI5dA==",
        "label": "CH-NA"
      }
    ]
  },
  {
    "id": "54498432",
    "league": "International - United League, Main Round",
    "team1": {
      "name": "BC Nizhny Novgorod"
    },
    "team2": {
      "name": "Parma Perm"
    },
    "kickoff_date": "live",
    "kickoff_time": "live",
    "match_date": "live",
    "match_time": "live",
    "duration": "live",
    "servers": [
      {
        "url": "https://multi.govoet.my.id/?iframe=aHR0cHM6Ly9zcG9ydC5pbnBsYXluZXQudGVjaC9saXZlc3RyZWFtLmh0bWw/c3JjPWFIUjBjSE02THk5emJXUXVjM0J2Y25Sd2JHRjVaWEl1YVc4dlpXMWlaV1F1Y0dod0x6OXRZWFJqYUY5cFpEMHhNek15TmpRM05pWnphejB4WXpsaFl6QXhKblI1Y0dVOWN5WndZWEpsYm5ROVpHVnRieTVwYm5Cc1lYbHVaWFF1WTI5dA==",
        "label": "CH-NA"
      }
    ]
  },
  {
    "id": "54494639",
    "league": "International - Europe Cup, Qualification",
    "team1": {
      "name": "Balkan Botevgrad"
    },
    "team2": {
      "name": "Rasta Vechta"
    },
    "kickoff_date": "live",
    "kickoff_time": "live",
    "match_date": "live",
    "match_time": "live",
    "duration": "live",
    "servers": [
      {
        "url": "https://multi.govoet.my.id/?iframe=aHR0cHM6Ly9zcG9ydC5pbnBsYXluZXQudGVjaC9saXZlc3RyZWFtLmh0bWw/c3JjPWFIUjBjSE02THk5emJXUXVjM0J2Y25Sd2JHRjVaWEl1YVc4dlpXMWlaV1F1Y0dod0x6OXRZWFJqYUY5cFpEMHhNek15TnpRMU1TWnphejB4WXpsaFl6QXhKblI1Y0dVOWN5WndZWEpsYm5ROVpHVnRieTVwYm5Cc1lYbHVaWFF1WTI5dA==",
        "label": "CH-NA"
      }
    ]
  },
  {
    "id": "53928683",
    "league": "International - Europe Cup, Qualification",
    "team1": {
      "name": "Anwil Wroclawek"
    },
    "team2": {
      "name": "KB Bashkimi"
    },
    "kickoff_date": "live",
    "kickoff_time": "live",
    "match_date": "live",
    "match_time": "live",
    "duration": "live",
    "servers": [
      {
        "url": "https://multi.govoet.my.id/?iframe=aHR0cHM6Ly9zcG9ydC5pbnBsYXluZXQudGVjaC9saXZlc3RyZWFtLmh0bWw/c3JjPWFIUjBjSE02THk5emJXUXVjM0J2Y25Sd2JHRjVaWEl1YVc4dlpXMWlaV1F1Y0dod0x6OXRZWFJqYUY5cFpEMHhNek15TnpRMU5DWnphejB4WXpsaFl6QXhKblI1Y0dVOWN5WndZWEpsYm5ROVpHVnRieTVwYm5Cc1lYbHVaWFF1WTI5dA==",
        "label": "CH-NA"
      }
    ]
  },
  {
    "id": "54494643",
    "league": "International - Europe Cup, Qualification",
    "team1": {
      "name": "BC Prievidza"
    },
    "team2": {
      "name": "KK Cibona"
    },
    "kickoff_date": "live",
    "kickoff_time": "live",
    "match_date": "live",
    "match_time": "live",
    "duration": "live",
    "servers": [
      {
        "url": "https://multi.govoet.my.id/?iframe=aHR0cHM6Ly9zcG9ydC5pbnBsYXluZXQudGVjaC9saXZlc3RyZWFtLmh0bWw/c3JjPWFIUjBjSE02THk5emJXUXVjM0J2Y25Sd2JHRjVaWEl1YVc4dlpXMWlaV1F1Y0dod0x6OXRZWFJqYUY5cFpEMHhNek15TnpRMU5TWnphejB4WXpsaFl6QXhKblI1Y0dVOWN5WndZWEpsYm5ROVpHVnRieTVwYm5Cc1lYbHVaWFF1WTI5dA==",
        "label": "CH-NA"
      }
    ]
  },
  {
    "id": "54494642",
    "league": "International - Europe Cup, Qualification",
    "team1": {
      "name": "Anorthosis Famagusta"
    },
    "team2": {
      "name": "Absheron BC"
    },
    "kickoff_date": "live",
    "kickoff_time": "live",
    "match_date": "live",
    "match_time": "live",
    "duration": "live",
    "servers": [
      {
        "url": "https://multi.govoet.my.id/?iframe=aHR0cHM6Ly9zcG9ydC5pbnBsYXluZXQudGVjaC9saXZlc3RyZWFtLmh0bWw/c3JjPWFIUjBjSE02THk5emJXUXVjM0J2Y25Sd2JHRjVaWEl1YVc4dlpXMWlaV1F1Y0dod0x6OXRZWFJqYUY5cFpEMHhNek15TnpRME9DWnphejB4WXpsaFl6QXhKblI1Y0dVOWN5WndZWEpsYm5ROVpHVnRieTVwYm5Cc1lYbHVaWFF1WTI5dA==",
        "label": "CH-NA"
      }
    ]
  },
  {
    "id": "54495101",
    "league": "Denmark - Basketligaen",
    "team1": {
      "name": "Svendborg Rabbits"
    },
    "team2": {
      "name": "Bakken Bears"
    },
    "kickoff_date": "live",
    "kickoff_time": "live",
    "match_date": "live",
    "match_time": "live",
    "duration": "live",
    "servers": [
      {
        "url": "https://multi.govoet.my.id/?iframe=aHR0cHM6Ly9zcG9ydC5pbnBsYXluZXQudGVjaC9saXZlc3RyZWFtLmh0bWw/c3JjPWFIUjBjSE02THk5emJXUXVjM0J2Y25Sd2JHRjVaWEl1YVc4dlpXMWlaV1F1Y0dod0x6OXRZWFJqYUY5cFpEMHhNek15T0RBeU5pWnphejB4WXpsaFl6QXhKblI1Y0dVOWN5WndZWEpsYm5ROVpHVnRieTVwYm5Cc1lYbHVaWFF1WTI5dA==",
        "label": "CH-NA"
      }
    ]
  },
  {
    "id": "54518065",
    "league": "Czech Republic - NBL",
    "team1": {
      "name": "Sokol Pisek"
    },
    "team2": {
      "name": "BK Olomoucko"
    },
    "kickoff_date": "live",
    "kickoff_time": "live",
    "match_date": "live",
    "match_time": "live",
    "duration": "live",
    "servers": [
      {
        "url": "https://multi.govoet.my.id/?iframe=aHR0cHM6Ly9zcG9ydC5pbnBsYXluZXQudGVjaC9saXZlc3RyZWFtLmh0bWw/c3JjPWFIUjBjSE02THk5emJXUXVjM0J2Y25Sd2JHRjVaWEl1YVc4dlpXMWlaV1F1Y0dod0x6OXRZWFJqYUY5cFpEMHhNek15TnpVeU5DWnphejB4WXpsaFl6QXhKblI1Y0dVOWN5WndZWEpsYm5ROVpHVnRieTVwYm5Cc1lYbHVaWFF1WTI5dA==",
        "label": "CH-NA"
      }
    ]
  },
  {
    "id": "54543770",
    "league": "Croatia - Premijer Liga",
    "team1": {
      "name": "Kk Split"
    },
    "team2": {
      "name": "Kk Dubrovnik"
    },
    "kickoff_date": "live",
    "kickoff_time": "live",
    "match_date": "live",
    "match_time": "live",
    "duration": "live",
    "servers": [
      {
        "url": "https://multi.govoet.my.id/?iframe=aHR0cHM6Ly9zcG9ydC5pbnBsYXluZXQudGVjaC9saXZlc3RyZWFtLmh0bWw/c3JjPWFIUjBjSE02THk5emJXUXVjM0J2Y25Sd2JHRjVaWEl1YVc4dlpXMWlaV1F1Y0dod0x6OXRZWFJqYUY5cFpEMHhNek15T0RjM015WnphejB4WXpsaFl6QXhKblI1Y0dVOWN5WndZWEpsYm5ROVpHVnRieTVwYm5Cc1lYbHVaWFF1WTI5dA==",
        "label": "CH-NA"
      }
    ]
  },
  {
    "id": "54470692",
    "league": "Romania - Liga Nationala",
    "team1": {
      "name": "Csm Corona Brasov"
    },
    "team2": {
      "name": "Steaua CSM Bucuresti"
    },
    "kickoff_date": "live",
    "kickoff_time": "live",
    "match_date": "live",
    "match_time": "live",
    "duration": "live",
    "servers": [
      {
        "url": "https://multi.govoet.my.id/?iframe=aHR0cHM6Ly9zcG9ydC5pbnBsYXluZXQudGVjaC9saXZlc3RyZWFtLmh0bWw/c3JjPWFIUjBjSE02THk5emJXUXVjM0J2Y25Sd2JHRjVaWEl1YVc4dlpXMWlaV1F1Y0dod0x6OXRZWFJqYUY5cFpEMHhNek15TnpRNE55WnphejB4WXpsaFl6QXhKblI1Y0dVOWN5WndZWEpsYm5ROVpHVnRieTVwYm5Cc1lYbHVaWFF1WTI5dA==",
        "label": "CH-NA"
      }
    ]
  },
  {
    "id": "54497071",
    "league": "Romania - Liga Nationala",
    "team1": {
      "name": "CSO Voluntari"
    },
    "team2": {
      "name": "CS Dinamo Bucuresti"
    },
    "kickoff_date": "live",
    "kickoff_time": "live",
    "match_date": "live",
    "match_time": "live",
    "duration": "live",
    "servers": [
      {
        "url": "https://multi.govoet.my.id/?iframe=aHR0cHM6Ly9zcG9ydC5pbnBsYXluZXQudGVjaC9saXZlc3RyZWFtLmh0bWw/c3JjPWFIUjBjSE02THk5emJXUXVjM0J2Y25Sd2JHRjVaWEl1YVc4dlpXMWlaV1F1Y0dod0x6OXRZWFJqYUY5cFpEMHhNek15TnpRNU1DWnphejB4WXpsaFl6QXhKblI1Y0dVOWN5WndZWEpsYm5ROVpHVnRieTVwYm5Cc1lYbHVaWFF1WTI5dA==",
        "label": "CH-NA"
      }
    ]
  },
  {
    "id": "54421869",
    "league": "Romania - Liga Nationala",
    "team1": {
      "name": "CS Valcea 1924 Rm Valcea"
    },
    "team2": {
      "name": "Municipal Galati"
    },
    "kickoff_date": "live",
    "kickoff_time": "live",
    "match_date": "live",
    "match_time": "live",
    "duration": "live",
    "servers": [
      {
        "url": "https://multi.govoet.my.id/?iframe=aHR0cHM6Ly9zcG9ydC5pbnBsYXluZXQudGVjaC9saXZlc3RyZWFtLmh0bWw/c3JjPWFIUjBjSE02THk5emJXUXVjM0J2Y25Sd2JHRjVaWEl1YVc4dlpXMWlaV1F1Y0dod0x6OXRZWFJqYUY5cFpEMHhNek15TnpRNU5TWnphejB4WXpsaFl6QXhKblI1Y0dVOWN5WndZWEpsYm5ROVpHVnRieTVwYm5Cc1lYbHVaWFF1WTI5dA==",
        "label": "CH-NA"
      }
    ]
  },
  {
    "id": "54497091",
    "league": "Romania - Liga Nationala",
    "team1": {
      "name": "Scm Universitatea Craiova"
    },
    "team2": {
      "name": "BC Timisoara"
    },
    "kickoff_date": "live",
    "kickoff_time": "live",
    "match_date": "live",
    "match_time": "live",
    "duration": "live",
    "servers": [
      {
        "url": "https://multi.govoet.my.id/?iframe=aHR0cHM6Ly9zcG9ydC5pbnBsYXluZXQudGVjaC9saXZlc3RyZWFtLmh0bWw/c3JjPWFIUjBjSE02THk5emJXUXVjM0J2Y25Sd2JHRjVaWEl1YVc4dlpXMWlaV1F1Y0dod0x6OXRZWFJqYUY5cFpEMHhNek15TnpRNU15WnphejB4WXpsaFl6QXhKblI1Y0dVOWN5WndZWEpsYm5ROVpHVnRieTVwYm5Cc1lYbHVaWFF1WTI5dA==",
        "label": "CH-NA"
      }
    ]
  },
  {
    "id": "54496802",
    "league": "Romania - Liga Nationala",
    "team1": {
      "name": "CS Rapid Bucuresti"
    },
    "team2": {
      "name": "CSM Targu Mures"
    },
    "kickoff_date": "live",
    "kickoff_time": "live",
    "match_date": "live",
    "match_time": "live",
    "duration": "live",
    "servers": [
      {
        "url": "https://multi.govoet.my.id/?iframe=aHR0cHM6Ly9zcG9ydC5pbnBsYXluZXQudGVjaC9saXZlc3RyZWFtLmh0bWw/c3JjPWFIUjBjSE02THk5emJXUXVjM0J2Y25Sd2JHRjVaWEl1YVc4dlpXMWlaV1F1Y0dod0x6OXRZWFJqYUY5cFpEMHhNek15TnpRNU55WnphejB4WXpsaFl6QXhKblI1Y0dVOWN5WndZWEpsYm5ROVpHVnRieTVwYm5Cc1lYbHVaWFF1WTI5dA==",
        "label": "CH-NA"
      }
    ]
  },
  {
    "id": "54497061",
    "league": "Romania - Liga Nationala",
    "team1": {
      "name": "Arges Pitesti"
    },
    "team2": {
      "name": "CSU Sibiu"
    },
    "kickoff_date": "live",
    "kickoff_time": "live",
    "match_date": "live",
    "match_time": "live",
    "duration": "live",
    "servers": [
      {
        "url": "https://multi.govoet.my.id/?iframe=aHR0cHM6Ly9zcG9ydC5pbnBsYXluZXQudGVjaC9saXZlc3RyZWFtLmh0bWw/c3JjPWFIUjBjSE02THk5emJXUXVjM0J2Y25Sd2JHRjVaWEl1YVc4dlpXMWlaV1F1Y0dod0x6OXRZWFJqYUY5cFpEMHhNek15TnpRNE5TWnphejB4WXpsaFl6QXhKblI1Y0dVOWN5WndZWEpsYm5ROVpHVnRieTVwYm5Cc1lYbHVaWFF1WTI5dA==",
        "label": "CH-NA"
      }
    ]
  },
  {
    "id": "54481184",
    "league": "Slovakia - Extraliga, Women",
    "team1": {
      "name": "08 Banska Bystrica W."
    },
    "team2": {
      "name": "SCP Ruzomberok W."
    },
    "kickoff_date": "live",
    "kickoff_time": "live",
    "match_date": "live",
    "match_time": "live",
    "duration": "live",
    "servers": [
      {
        "url": "https://multi.govoet.my.id/?iframe=aHR0cHM6Ly9zcG9ydC5pbnBsYXluZXQudGVjaC9saXZlc3RyZWFtLmh0bWw/c3JjPWFIUjBjSE02THk5emJXUXVjM0J2Y25Sd2JHRjVaWEl1YVc4dlpXMWlaV1F1Y0dod0x6OXRZWFJqYUY5cFpEMHhNek14T0RnM01DWnphejB4WXpsaFl6QXhKblI1Y0dVOWN5WndZWEpsYm5ROVpHVnRieTVwYm5Cc1lYbHVaWFF1WTI5dA==",
        "label": "CH-NA"
      }
    ]
  },
  {
    "id": "53490015",
    "league": "Russia - Superleague, 1st Division",
    "team1": {
      "name": "Bars-Rgeu Rostov NA Donu"
    },
    "team2": {
      "name": "Barnaul Altayskiy Kray"
    },
    "kickoff_date": "live",
    "kickoff_time": "live",
    "match_date": "live",
    "match_time": "live",
    "duration": "live",
    "servers": [
      {
        "url": "https://multi.govoet.my.id/?iframe=aHR0cHM6Ly9zcG9ydC5pbnBsYXluZXQudGVjaC9saXZlc3RyZWFtLmh0bWw/c3JjPWFIUjBjSE02THk5emJXUXVjM0J2Y25Sd2JHRjVaWEl1YVc4dlpXMWlaV1F1Y0dod0x6OXRZWFJqYUY5cFpEMHhNek15TmpRNU1pWnphejB4WXpsaFl6QXhKblI1Y0dVOWN5WndZWEpsYm5ROVpHVnRieTVwYm5Cc1lYbHVaWFF1WTI5dA==",
        "label": "CH-NA"
      }
    ]
  },
  {
    "id": "54091817",
    "league": "Challenger - Mouilleron Le Captif, France",
    "team1": {
      "name": "Kypson, Patrick"
    },
    "team2": {
      "name": "Herbert, Pierre-hugues"
    },
    "kickoff_date": "live",
    "kickoff_time": "live",
    "match_date": "live",
    "match_time": "live",
    "duration": "live",
    "servers": [
      {
        "url": "https://multi.govoet.my.id/?iframe=aHR0cHM6Ly9zcG9ydC5pbnBsYXluZXQudGVjaC9saXZlc3RyZWFtLmh0bWw/c3JjPWFIUjBjSE02THk5emJXUXVjM0J2Y25Sd2JHRjVaWEl1YVc4dlpXMWlaV1F1Y0dod0x6OXRZWFJqYUY5cFpEMHhNek16TURJd01TWnphejB4WXpsaFl6QXhKblI1Y0dVOWN5WndZWEpsYm5ROVpHVnRieTVwYm5Cc1lYbHVaWFF1WTI5dA==",
        "label": "CH-NA"
      }
    ]
  },
  {
    "id": "54051036",
    "league": "Russia - KHL",
    "team1": {
      "name": "SKA Saint Petersburg"
    },
    "team2": {
      "name": "Torpedo N. Novgorod"
    },
    "kickoff_date": "live",
    "kickoff_time": "live",
    "match_date": "live",
    "match_time": "live",
    "duration": "live",
    "servers": [
      {
        "url": "https://multi.govoet.my.id/?iframe=aHR0cHM6Ly9zcG9ydC5pbnBsYXluZXQudGVjaC9saXZlc3RyZWFtLmh0bWw/c3JjPWFIUjBjSE02THk5emJXUXVjM0J2Y25Sd2JHRjVaWEl1YVc4dlpXMWlaV1F1Y0dod0x6OXRZWFJqYUY5cFpEMHhNekk1T0RRek1TWnphejB4WXpsaFl6QXhKblI1Y0dVOWN5WndZWEpsYm5ROVpHVnRieTVwYm5Cc1lYbHVaWFF1WTI5dA==",
        "label": "CH-NA"
      }
    ]
  },
  {
    "id": "51660106",
    "league": "Russia - KHL",
    "team1": {
      "name": "HC Dinamo Minsk"
    },
    "team2": {
      "name": "Severstal Cherepovets"
    },
    "kickoff_date": "live",
    "kickoff_time": "live",
    "match_date": "live",
    "match_time": "live",
    "duration": "live",
    "servers": [
      {
        "url": "https://multi.govoet.my.id/?iframe=aHR0cHM6Ly9zcG9ydC5pbnBsYXluZXQudGVjaC9saXZlc3RyZWFtLmh0bWw/c3JjPWFIUjBjSE02THk5emJXUXVjM0J2Y25Sd2JHRjVaWEl1YVc4dlpXMWlaV1F1Y0dod0x6OXRZWFJqYUY5cFpEMHhNekk1T0RRek1DWnphejB4WXpsaFl6QXhKblI1Y0dVOWN5WndZWEpsYm5ROVpHVnRieTVwYm5Cc1lYbHVaWFF1WTI5dA==",
        "label": "CH-NA"
      }
    ]
  },
  {
    "id": "51660108",
    "league": "Russia - VHL",
    "team1": {
      "name": "HK Torpedo Gorkii"
    },
    "team2": {
      "name": "Ska-Neva Saint Petersburg"
    },
    "kickoff_date": "live",
    "kickoff_time": "live",
    "match_date": "live",
    "match_time": "live",
    "duration": "live",
    "servers": [
      {
        "url": "https://multi.govoet.my.id/?iframe=aHR0cHM6Ly9zcG9ydC5pbnBsYXluZXQudGVjaC9saXZlc3RyZWFtLmh0bWw/c3JjPWFIUjBjSE02THk5emJXUXVjM0J2Y25Sd2JHRjVaWEl1YVc4dlpXMWlaV1F1Y0dod0x6OXRZWFJqYUY5cFpEMHhNek14T0RRek15WnphejB4WXpsaFl6QXhKblI1Y0dVOWN5WndZWEpsYm5ROVpHVnRieTVwYm5Cc1lYbHVaWFF1WTI5dA==",
        "label": "CH-NA"
      }
    ]
  },
  {
    "id": "52292864",
    "league": "Russia - MHL",
    "team1": {
      "name": "Irbis Kazan"
    },
    "team2": {
      "name": "MHC Dinamo Saint Petersburg"
    },
    "kickoff_date": "live",
    "kickoff_time": "live",
    "match_date": "live",
    "match_time": "live",
    "duration": "live",
    "servers": [
      {
        "url": "https://multi.govoet.my.id/?iframe=aHR0cHM6Ly9zcG9ydC5pbnBsYXluZXQudGVjaC9saXZlc3RyZWFtLmh0bWw/c3JjPWFIUjBjSE02THk5emJXUXVjM0J2Y25Sd2JHRjVaWEl1YVc4dlpXMWlaV1F1Y0dod0x6OXRZWFJqYUY5cFpEMHhNek14T0RRek9TWnphejB4WXpsaFl6QXhKblI1Y0dVOWN5WndZWEpsYm5ROVpHVnRieTVwYm5Cc1lYbHVaWFF1WTI5dA==",
        "label": "CH-NA"
      }
    ]
  },
  {
    "id": "51660112",
    "league": "Russia - MHL",
    "team1": {
      "name": "Krasnaya Armiya"
    },
    "team2": {
      "name": "Akm-junior Novomoskovsk"
    },
    "kickoff_date": "live",
    "kickoff_time": "live",
    "match_date": "live",
    "match_time": "live",
    "duration": "live",
    "servers": [
      {
        "url": "https://multi.govoet.my.id/?iframe=aHR0cHM6Ly9zcG9ydC5pbnBsYXluZXQudGVjaC9saXZlc3RyZWFtLmh0bWw/c3JjPWFIUjBjSE02THk5emJXUXVjM0J2Y25Sd2JHRjVaWEl1YVc4dlpXMWlaV1F1Y0dod0x6OXRZWFJqYUY5cFpEMHhNek14T0RRME1DWnphejB4WXpsaFl6QXhKblI1Y0dVOWN5WndZWEpsYm5ROVpHVnRieTVwYm5Cc1lYbHVaWFF1WTI5dA==",
        "label": "CH-NA"
      }
    ]
  },
  {
    "id": "51661903",
    "league": "Finland - Liiga",
    "team1": {
      "name": "HIFK Helsinki"
    },
    "team2": {
      "name": "KooKoo"
    },
    "kickoff_date": "live",
    "kickoff_time": "live",
    "match_date": "live",
    "match_time": "live",
    "duration": "live",
    "servers": [
      {
        "url": "https://multi.govoet.my.id/?iframe=aHR0cHM6Ly9zcG9ydC5pbnBsYXluZXQudGVjaC9saXZlc3RyZWFtLmh0bWw/c3JjPWFIUjBjSE02THk5emJXUXVjM0J2Y25Sd2JHRjVaWEl1YVc4dlpXMWlaV1F1Y0dod0x6OXRZWFJqYUY5cFpEMHhNek14T0RRMU1pWnphejB4WXpsaFl6QXhKblI1Y0dVOWN5WndZWEpsYm5ROVpHVnRieTVwYm5Cc1lYbHVaWFF1WTI5dA==",
        "label": "CH-NA"
      }
    ]
  },
  {
    "id": "51661900",
    "league": "Finland - Liiga",
    "team1": {
      "name": "SaiPa Lappeenranta"
    },
    "team2": {
      "name": "HPK Hameenlinna"
    },
    "kickoff_date": "live",
    "kickoff_time": "live",
    "match_date": "live",
    "match_time": "live",
    "duration": "live",
    "servers": [
      {
        "url": "https://multi.govoet.my.id/?iframe=aHR0cHM6Ly9zcG9ydC5pbnBsYXluZXQudGVjaC9saXZlc3RyZWFtLmh0bWw/c3JjPWFIUjBjSE02THk5emJXUXVjM0J2Y25Sd2JHRjVaWEl1YVc4dlpXMWlaV1F1Y0dod0x6OXRZWFJqYUY5cFpEMHhNek14T0RRMU5DWnphejB4WXpsaFl6QXhKblI1Y0dVOWN5WndZWEpsYm5ROVpHVnRieTVwYm5Cc1lYbHVaWFF1WTI5dA==",
        "label": "CH-NA"
      }
    ]
  },
  {
    "id": "54267460",
    "league": "Sweden - Hockey Allsvenskan",
    "team1": {
      "name": "IF Bjorkloven"
    },
    "team2": {
      "name": "Nybro Vikings IF"
    },
    "kickoff_date": "live",
    "kickoff_time": "live",
    "match_date": "live",
    "match_time": "live",
    "duration": "live",
    "servers": [
      {
        "url": "https://multi.govoet.my.id/?iframe=aHR0cHM6Ly9zcG9ydC5pbnBsYXluZXQudGVjaC9saXZlc3RyZWFtLmh0bWw/c3JjPWFIUjBjSE02THk5emJXUXVjM0J2Y25Sd2JHRjVaWEl1YVc4dlpXMWlaV1F1Y0dod0x6OXRZWFJqYUY5cFpEMHhNek15TXpnMk15WnphejB4WXpsaFl6QXhKblI1Y0dVOWN5WndZWEpsYm5ROVpHVnRieTVwYm5Cc1lYbHVaWFF1WTI5dA==",
        "label": "CH-NA"
      }
    ]
  },
  {
    "id": "54267461",
    "league": "Sweden - Hockey Allsvenskan",
    "team1": {
      "name": "Sodertalje SK"
    },
    "team2": {
      "name": "VIK Vasteraas"
    },
    "kickoff_date": "live",
    "kickoff_time": "live",
    "match_date": "live",
    "match_time": "live",
    "duration": "live",
    "servers": [
      {
        "url": "https://multi.govoet.my.id/?iframe=aHR0cHM6Ly9zcG9ydC5pbnBsYXluZXQudGVjaC9saXZlc3RyZWFtLmh0bWw/c3JjPWFIUjBjSE02THk5emJXUXVjM0J2Y25Sd2JHRjVaWEl1YVc4dlpXMWlaV1F1Y0dod0x6OXRZWFJqYUY5cFpEMHhNek15TXpnMk1pWnphejB4WXpsaFl6QXhKblI1Y0dVOWN5WndZWEpsYm5ROVpHVnRieTVwYm5Cc1lYbHVaWFF1WTI5dA==",
        "label": "CH-NA"
      }
    ]
  },
  {
    "id": "54267463",
    "league": "Sweden - Hockey Allsvenskan",
    "team1": {
      "name": "Vimmerby HC"
    },
    "team2": {
      "name": "BIK Karlskoga"
    },
    "kickoff_date": "live",
    "kickoff_time": "live",
    "match_date": "live",
    "match_time": "live",
    "duration": "live",
    "servers": [
      {
        "url": "https://multi.govoet.my.id/?iframe=aHR0cHM6Ly9zcG9ydC5pbnBsYXluZXQudGVjaC9saXZlc3RyZWFtLmh0bWw/c3JjPWFIUjBjSE02THk5emJXUXVjM0J2Y25Sd2JHRjVaWEl1YVc4dlpXMWlaV1F1Y0dod0x6OXRZWFJqYUY5cFpEMHhNek15TXpnMk5TWnphejB4WXpsaFl6QXhKblI1Y0dVOWN5WndZWEpsYm5ROVpHVnRieTVwYm5Cc1lYbHVaWFF1WTI5dA==",
        "label": "CH-NA"
      }
    ]
  },
  {
    "id": "54267462",
    "league": "Sweden - Hockey Allsvenskan",
    "team1": {
      "name": "Ostersunds IK"
    },
    "team2": {
      "name": "Kalmar HC"
    },
    "kickoff_date": "live",
    "kickoff_time": "live",
    "match_date": "live",
    "match_time": "live",
    "duration": "live",
    "servers": [
      {
        "url": "https://multi.govoet.my.id/?iframe=aHR0cHM6Ly9zcG9ydC5pbnBsYXluZXQudGVjaC9saXZlc3RyZWFtLmh0bWw/c3JjPWFIUjBjSE02THk5emJXUXVjM0J2Y25Sd2JHRjVaWEl1YVc4dlpXMWlaV1F1Y0dod0x6OXRZWFJqYUY5cFpEMHhNek15TXpnMk1TWnphejB4WXpsaFl6QXhKblI1Y0dVOWN5WndZWEpsYm5ROVpHVnRieTVwYm5Cc1lYbHVaWFF1WTI5dA==",
        "label": "CH-NA"
      }
    ]
  },
  {
    "id": "54407112",
    "league": "Sweden - Hockey Allsvenskan",
    "team1": {
      "name": "AIK IF"
    },
    "team2": {
      "name": "IK Oskarshamn"
    },
    "kickoff_date": "live",
    "kickoff_time": "live",
    "match_date": "live",
    "match_time": "live",
    "duration": "live",
    "servers": [
      {
        "url": "https://multi.govoet.my.id/?iframe=aHR0cHM6Ly9zcG9ydC5pbnBsYXluZXQudGVjaC9saXZlc3RyZWFtLmh0bWw/c3JjPWFIUjBjSE02THk5emJXUXVjM0J2Y25Sd2JHRjVaWEl1YVc4dlpXMWlaV1F1Y0dod0x6OXRZWFJqYUY5cFpEMHhNek15TXpnMk5DWnphejB4WXpsaFl6QXhKblI1Y0dVOWN5WndZWEpsYm5ROVpHVnRieTVwYm5Cc1lYbHVaWFF1WTI5dA==",
        "label": "CH-NA"
      }
    ]
  },
  {
    "id": "53843205",
    "league": "Czech Republic - 1st Liga",
    "team1": {
      "name": "HC Dynamo Pardubice B"
    },
    "team2": {
      "name": "HC Dukla Jihlava"
    },
    "kickoff_date": "live",
    "kickoff_time": "live",
    "match_date": "live",
    "match_time": "live",
    "duration": "live",
    "servers": [
      {
        "url": "https://multi.govoet.my.id/?iframe=aHR0cHM6Ly9zcG9ydC5pbnBsYXluZXQudGVjaC9saXZlc3RyZWFtLmh0bWw/c3JjPWFIUjBjSE02THk5emJXUXVjM0J2Y25Sd2JHRjVaWEl1YVc4dlpXMWlaV1F1Y0dod0x6OXRZWFJqYUY5cFpEMHhNek16TXpVNE5pWnphejB4WXpsaFl6QXhKblI1Y0dVOWN5WndZWEpsYm5ROVpHVnRieTVwYm5Cc1lYbHVaWFF1WTI5dA==",
        "label": "CH-NA"
      }
    ]
  },
  {
    "id": "54364105",
    "league": "Slovakia - 1st Liga",
    "team1": {
      "name": "HK Spartak Dubnica"
    },
    "team2": {
      "name": "95 Povazska Bystrica"
    },
    "kickoff_date": "live",
    "kickoff_time": "live",
    "match_date": "live",
    "match_time": "live",
    "duration": "live",
    "servers": [
      {
        "url": "https://multi.govoet.my.id/?iframe=aHR0cHM6Ly9zcG9ydC5pbnBsYXluZXQudGVjaC9saXZlc3RyZWFtLmh0bWw/c3JjPWFIUjBjSE02THk5emJXUXVjM0J2Y25Sd2JHRjVaWEl1YVc4dlpXMWlaV1F1Y0dod0x6OXRZWFJqYUY5cFpEMHhNek14T0RRME9DWnphejB4WXpsaFl6QXhKblI1Y0dVOWN5WndZWEpsYm5ROVpHVnRieTVwYm5Cc1lYbHVaWFF1WTI5dA==",
        "label": "CH-NA"
      }
    ]
  },
  {
    "id": "53843186",
    "league": "Slovakia - 1st Liga",
    "team1": {
      "name": "HC 07 Detva"
    },
    "team2": {
      "name": "HK 36 Skalica"
    },
    "kickoff_date": "live",
    "kickoff_time": "live",
    "match_date": "live",
    "match_time": "live",
    "duration": "live",
    "servers": [
      {
        "url": "https://multi.govoet.my.id/?iframe=aHR0cHM6Ly9zcG9ydC5pbnBsYXluZXQudGVjaC9saXZlc3RyZWFtLmh0bWw/c3JjPWFIUjBjSE02THk5emJXUXVjM0J2Y25Sd2JHRjVaWEl1YVc4dlpXMWlaV1F1Y0dod0x6OXRZWFJqYUY5cFpEMHhNek14T0RRME55WnphejB4WXpsaFl6QXhKblI1Y0dVOWN5WndZWEpsYm5ROVpHVnRieTVwYm5Cc1lYbHVaWFF1WTI5dA==",
        "label": "CH-NA"
      }
    ]
  },
  {
    "id": "53843190",
    "league": "Slovakia - 1st Liga",
    "team1": {
      "name": "Hk Msk Indian Ziar Nad Hronom"
    },
    "team2": {
      "name": "HC Topolcany"
    },
    "kickoff_date": "live",
    "kickoff_time": "live",
    "match_date": "live",
    "match_time": "live",
    "duration": "live",
    "servers": [
      {
        "url": "https://multi.govoet.my.id/?iframe=aHR0cHM6Ly9zcG9ydC5pbnBsYXluZXQudGVjaC9saXZlc3RyZWFtLmh0bWw/c3JjPWFIUjBjSE02THk5emJXUXVjM0J2Y25Sd2JHRjVaWEl1YVc4dlpXMWlaV1F1Y0dod0x6OXRZWFJqYUY5cFpEMHhNek14T0RRMU1DWnphejB4WXpsaFl6QXhKblI1Y0dVOWN5WndZWEpsYm5ROVpHVnRieTVwYm5Cc1lYbHVaWFF1WTI5dA==",
        "label": "CH-NA"
      }
    ]
  },
  {
    "id": "54446815",
    "league": "Belarus - Extraliga",
    "team1": {
      "name": "HK Brest"
    },
    "team2": {
      "name": "HK Gomel"
    },
    "kickoff_date": "live",
    "kickoff_time": "live",
    "match_date": "live",
    "match_time": "live",
    "duration": "live",
    "servers": [
      {
        "url": "https://multi.govoet.my.id/?iframe=aHR0cHM6Ly9zcG9ydC5pbnBsYXluZXQudGVjaC9saXZlc3RyZWFtLmh0bWw/c3JjPWFIUjBjSE02THk5emJXUXVjM0J2Y25Sd2JHRjVaWEl1YVc4dlpXMWlaV1F1Y0dod0x6OXRZWFJqYUY5cFpEMHhNek14T0RReU1TWnphejB4WXpsaFl6QXhKblI1Y0dVOWN5WndZWEpsYm5ROVpHVnRieTVwYm5Cc1lYbHVaWFF1WTI5dA==",
        "label": "CH-NA"
      }
    ]
  },
  {
    "id": "54369534",
    "league": "Latvia - Latvian Hockey League",
    "team1": {
      "name": "HK Zemgale/Llu"
    },
    "team2": {
      "name": "HK Prizma"
    },
    "kickoff_date": "live",
    "kickoff_time": "live",
    "match_date": "live",
    "match_time": "live",
    "duration": "live",
    "servers": [
      {
        "url": "https://multi.govoet.my.id/?iframe=aHR0cHM6Ly9zcG9ydC5pbnBsYXluZXQudGVjaC9saXZlc3RyZWFtLmh0bWw/c3JjPWFIUjBjSE02THk5emJXUXVjM0J2Y25Sd2JHRjVaWEl1YVc4dlpXMWlaV1F1Y0dod0x6OXRZWFJqYUY5cFpEMHhNek14T0RReU5pWnphejB4WXpsaFl6QXhKblI1Y0dVOWN5WndZWEpsYm5ROVpHVnRieTVwYm5Cc1lYbHVaWFF1WTI5dA==",
        "label": "CH-NA"
      }
    ]
  },
  {
    "id": "54478329",
    "league": "International - MOL Liga, Women",
    "team1": {
      "name": "HK Slovan Duslo Sala W."
    },
    "team2": {
      "name": "DHC Sokol Poruba W."
    },
    "kickoff_date": "live",
    "kickoff_time": "live",
    "match_date": "live",
    "match_time": "live",
    "duration": "live",
    "servers": [
      {
        "url": "https://multi.govoet.my.id/?iframe=aHR0cHM6Ly9zcG9ydC5pbnBsYXluZXQudGVjaC9saXZlc3RyZWFtLmh0bWw/c3JjPWFIUjBjSE02THk5emJXUXVjM0J2Y25Sd2JHRjVaWEl1YVc4dlpXMWlaV1F1Y0dod0x6OXRZWFJqYUY5cFpEMHhNek14T1RNd01TWnphejB4WXpsaFl6QXhKblI1Y0dVOWN5WndZWEpsYm5ROVpHVnRieTVwYm5Cc1lYbHVaWFF1WTI5dA==",
        "label": "CH-NA"
      }
    ]
  },
  {
    "id": "52514136",
    "league": "Germany - Bundesliga, Women",
    "team1": {
      "name": "HSG Bensheim/Auerbach W."
    },
    "team2": {
      "name": "Bvb Dortmund Handball W."
    },
    "kickoff_date": "live",
    "kickoff_time": "live",
    "match_date": "live",
    "match_time": "live",
    "duration": "live",
    "servers": [
      {
        "url": "https://multi.govoet.my.id/?iframe=aHR0cHM6Ly9zcG9ydC5pbnBsYXluZXQudGVjaC9saXZlc3RyZWFtLmh0bWw/c3JjPWFIUjBjSE02THk5emJXUXVjM0J2Y25Sd2JHRjVaWEl1YVc4dlpXMWlaV1F1Y0dod0x6OXRZWFJqYUY5cFpEMHhNek14T1RBNU9TWnphejB4WXpsaFl6QXhKblI1Y0dVOWN5WndZWEpsYm5ROVpHVnRieTVwYm5Cc1lYbHVaWFF1WTI5dA==",
        "label": "CH-NA"
      }
    ]
  },
  {
    "id": "54127313",
    "league": "Slovenia - 1. liga",
    "team1": {
      "name": "RK Trimo Trebnje"
    },
    "team2": {
      "name": "Celje"
    },
    "kickoff_date": "live",
    "kickoff_time": "live",
    "match_date": "live",
    "match_time": "live",
    "duration": "live",
    "servers": [
      {
        "url": "https://multi.govoet.my.id/?iframe=aHR0cHM6Ly9zcG9ydC5pbnBsYXluZXQudGVjaC9saXZlc3RyZWFtLmh0bWw/c3JjPWFIUjBjSE02THk5emJXUXVjM0J2Y25Sd2JHRjVaWEl1YVc4dlpXMWlaV1F1Y0dod0x6OXRZWFJqYUY5cFpEMHhNek15TkRBek5TWnphejB4WXpsaFl6QXhKblI1Y0dVOWN5WndZWEpsYm5ROVpHVnRieTVwYm5Cc1lYbHVaWFF1WTI5dA==",
        "label": "CH-NA"
      }
    ]
  },
  {
    "id": "54407129",
    "league": "Slovenia - 1. liga",
    "team1": {
      "name": "RK Prevent Slovenj Gradec"
    },
    "team2": {
      "name": "Rd Ribnica Riko Hise"
    },
    "kickoff_date": "live",
    "kickoff_time": "live",
    "match_date": "live",
    "match_time": "live",
    "duration": "live",
    "servers": [
      {
        "url": "https://multi.govoet.my.id/?iframe=aHR0cHM6Ly9zcG9ydC5pbnBsYXluZXQudGVjaC9saXZlc3RyZWFtLmh0bWw/c3JjPWFIUjBjSE02THk5emJXUXVjM0J2Y25Sd2JHRjVaWEl1YVc4dlpXMWlaV1F1Y0dod0x6OXRZWFJqYUY5cFpEMHhNek15TkRBeU9TWnphejB4WXpsaFl6QXhKblI1Y0dVOWN5WndZWEpsYm5ROVpHVnRieTVwYm5Cc1lYbHVaWFF1WTI5dA==",
        "label": "CH-NA"
      }
    ]
  },
  {
    "id": "54127321",
    "league": "Slovenia - 1. liga",
    "team1": {
      "name": "Rd Urbanscape Loka"
    },
    "team2": {
      "name": "Mrk Krka"
    },
    "kickoff_date": "live",
    "kickoff_time": "live",
    "match_date": "live",
    "match_time": "live",
    "duration": "live",
    "servers": [
      {
        "url": "https://multi.govoet.my.id/?iframe=aHR0cHM6Ly9zcG9ydC5pbnBsYXluZXQudGVjaC9saXZlc3RyZWFtLmh0bWw/c3JjPWFIUjBjSE02THk5emJXUXVjM0J2Y25Sd2JHRjVaWEl1YVc4dlpXMWlaV1F1Y0dod0x6OXRZWFJqYUY5cFpEMHhNek15TkRBME5TWnphejB4WXpsaFl6QXhKblI1Y0dVOWN5WndZWEpsYm5ROVpHVnRieTVwYm5Cc1lYbHVaWFF1WTI5dA==",
        "label": "CH-NA"
      }
    ]
  },
  {
    "id": "54127315",
    "league": "Serbia - Superliga, Women",
    "team1": {
      "name": "Zeleznicar W."
    },
    "team2": {
      "name": "Mladost NP W."
    },
    "kickoff_date": "live",
    "kickoff_time": "live",
    "match_date": "live",
    "match_time": "live",
    "duration": "live",
    "servers": [
      {
        "url": "https://multi.govoet.my.id/?iframe=aHR0cHM6Ly9zcG9ydC5pbnBsYXluZXQudGVjaC9saXZlc3RyZWFtLmh0bWw/c3JjPWFIUjBjSE02THk5emJXUXVjM0J2Y25Sd2JHRjVaWEl1YVc4dlpXMWlaV1F1Y0dod0x6OXRZWFJqYUY5cFpEMHhNek15TnpZeU9DWnphejB4WXpsaFl6QXhKblI1Y0dVOWN5WndZWEpsYm5ROVpHVnRieTVwYm5Cc1lYbHVaWFF1WTI5dA==",
        "label": "CH-NA"
      }
    ]
  },
  {
    "id": "54040230",
    "league": "International - UEFA U19 Futsal EURO Qualif, Group 5",
    "team1": {
      "name": "Italy U19"
    },
    "team2": {
      "name": "Ukraine U19"
    },
    "kickoff_date": "live",
    "kickoff_time": "live",
    "match_date": "live",
    "match_time": "live",
    "duration": "live",
    "servers": [
      {
        "url": "https://multi.govoet.my.id/?iframe=aHR0cHM6Ly9zcG9ydC5pbnBsYXluZXQudGVjaC9saXZlc3RyZWFtLmh0bWw/c3JjPWFIUjBjSE02THk5emJXUXVjM0J2Y25Sd2JHRjVaWEl1YVc4dlpXMWlaV1F1Y0dod0x6OXRZWFJqYUY5cFpEMHhNek15TkRVd09DWnphejB4WXpsaFl6QXhKblI1Y0dVOWN5WndZWEpsYm5ROVpHVnRieTVwYm5Cc1lYbHVaWFF1WTI5dA==",
        "label": "CH-NA"
      }
    ]
  },
  {
    "id": "54335841",
    "league": "Russia - Superliga",
    "team1": {
      "name": "Novaja Generacija"
    },
    "team2": {
      "name": "LKS Lipetskaya Oblast"
    },
    "kickoff_date": "live",
    "kickoff_time": "live",
    "match_date": "live",
    "match_time": "live",
    "duration": "live",
    "servers": [
      {
        "url": "https://multi.govoet.my.id/?iframe=aHR0cHM6Ly9zcG9ydC5pbnBsYXluZXQudGVjaC9saXZlc3RyZWFtLmh0bWw/c3JjPWFIUjBjSE02THk5emJXUXVjM0J2Y25Sd2JHRjVaWEl1YVc4dlpXMWlaV1F1Y0dod0x6OXRZWFJqYUY5cFpEMHhNek15TnpVNE5pWnphejB4WXpsaFl6QXhKblI1Y0dVOWN5WndZWEpsYm5ROVpHVnRieTVwYm5Cc1lYbHVaWFF1WTI5dA==",
        "label": "CH-NA"
      }
    ]
  },
  {
    "id": "54407155",
    "league": "Poland - Ekstraklasa",
    "team1": {
      "name": "Piast Gliwice"
    },
    "team2": {
      "name": "BTS Bielsko-Biała"
    },
    "kickoff_date": "live",
    "kickoff_time": "live",
    "match_date": "live",
    "match_time": "live",
    "duration": "live",
    "servers": [
      {
        "url": "https://multi.govoet.my.id/?iframe=aHR0cHM6Ly9zcG9ydC5pbnBsYXluZXQudGVjaC9saXZlc3RyZWFtLmh0bWw/c3JjPWFIUjBjSE02THk5emJXUXVjM0J2Y25Sd2JHRjVaWEl1YVc4dlpXMWlaV1F1Y0dod0x6OXRZWFJqYUY5cFpEMHhNek15TnpVM055WnphejB4WXpsaFl6QXhKblI1Y0dVOWN5WndZWEpsYm5ROVpHVnRieTVwYm5Cc1lYbHVaWFF1WTI5dA==",
        "label": "CH-NA"
      }
    ]
  },
  {
    "id": "54517771",
    "league": "International - TT Cup",
    "team1": {
      "name": "Caban, Jakub"
    },
    "team2": {
      "name": "Kedzierski, Piotr"
    },
    "kickoff_date": "live",
    "kickoff_time": "live",
    "match_date": "live",
    "match_time": "live",
    "duration": "live",
    "servers": [
      {
        "url": "https://multi.govoet.my.id/?iframe=aHR0cHM6Ly9zcG9ydC5pbnBsYXluZXQudGVjaC9saXZlc3RyZWFtLmh0bWw/c3JjPWFIUjBjSE02THk5emJXUXVjM0J2Y25Sd2JHRjVaWEl1YVc4dlpXMWlaV1F1Y0dod0x6OXRZWFJqYUY5cFpEMHhNek16TVRVek15WnphejB4WXpsaFl6QXhKblI1Y0dVOWN5WndZWEpsYm5ROVpHVnRieTVwYm5Cc1lYbHVaWFF1WTI5dA==",
        "label": "CH-NA"
      }
    ]
  },
  {
    "id": "54495195",
    "league": "International - TT Elite Series",
    "team1": {
      "name": "Krupa, Sebastian"
    },
    "team2": {
      "name": "Lebek, Marian"
    },
    "kickoff_date": "live",
    "kickoff_time": "live",
    "match_date": "live",
    "match_time": "live",
    "duration": "live",
    "servers": [
      {
        "url": "https://multi.govoet.my.id/?iframe=aHR0cHM6Ly9zcG9ydC5pbnBsYXluZXQudGVjaC9saXZlc3RyZWFtLmh0bWw/c3JjPWFIUjBjSE02THk5emJXUXVjM0J2Y25Sd2JHRjVaWEl1YVc4dlpXMWlaV1F1Y0dod0x6OXRZWFJqYUY5cFpEMHhNek16TWpjMk1TWnphejB4WXpsaFl6QXhKblI1Y0dVOWN5WndZWEpsYm5ROVpHVnRieTVwYm5Cc1lYbHVaWFF1WTI5dA==",
        "label": "CH-NA"
      }
    ]
  },
  {
    "id": "54533602",
    "league": "Tournaments - ESL Pro League Qualifiers",
    "team1": {
      "name": "FURIA"
    },
    "team2": {
      "name": "m80"
    },
    "kickoff_date": "live",
    "kickoff_time": "live",
    "match_date": "live",
    "match_time": "live",
    "duration": "live",
    "servers": [
      {
        "url": "https://multi.govoet.my.id/?iframe=aHR0cHM6Ly9zcG9ydC5pbnBsYXluZXQudGVjaC9saXZlc3RyZWFtLmh0bWw/c3JjPWFIUjBjSE02THk5d2JHRjVaWEl1ZEhkcGRHTm9MblIyTHo5amFHRnVibVZzUFdWemJHTnpKbkJoY21WdWREMWtaVzF2TG1sdWNHeGhlVzVsZEM1amIyMD0=",
        "label": "CH-NA"
      }
    ]
  },
  {
    "id": "54533549",
    "league": "Tournaments - ESL Pro League Qualifiers",
    "team1": {
      "name": "Legacy"
    },
    "team2": {
      "name": "gentle mates"
    },
    "kickoff_date": "live",
    "kickoff_time": "live",
    "match_date": "live",
    "match_time": "live",
    "duration": "live",
    "servers": [
      {
        "url": "https://multi.govoet.my.id/?iframe=aHR0cHM6Ly9zcG9ydC5pbnBsYXluZXQudGVjaC9saXZlc3RyZWFtLmh0bWw/c3JjPWFIUjBjSE02THk5d2JHRjVaWEl1ZEhkcGRHTm9MblIyTHo5amFHRnVibVZzUFdWemJHTnpZaVp3WVhKbGJuUTlaR1Z0Ynk1cGJuQnNZWGx1WlhRdVkyOXQ=",
        "label": "CH-NA"
      }
    ]
  },
  {
    "id": "54473879",
    "league": "Tournaments - CCT Series",
    "team1": {
      "name": "Gun5 Esports"
    },
    "team2": {
      "name": "eyeballers"
    },
    "kickoff_date": "live",
    "kickoff_time": "live",
    "match_date": "live",
    "match_time": "live",
    "duration": "live",
    "servers": [
      {
        "url": "https://multi.govoet.my.id/?iframe=aHR0cHM6Ly9zcG9ydC5pbnBsYXluZXQudGVjaC9saXZlc3RyZWFtLmh0bWw/c3JjPWFIUjBjSE02THk5d2JHRjVaWEl1ZEhkcGRHTm9MblIyTHo5amFHRnVibVZzUFdWemNHOXlkSE4wZFdScGIyNG1jR0Z5Wlc1MFBXUmxiVzh1YVc1d2JHRjVibVYwTG1OdmJRPT0=",
        "label": "CH-NA"
      }
    ]
  },
  {
    "id": "54540944",
    "league": "Tournaments - The Proving Grounds",
    "team1": {
      "name": "Tricked"
    },
    "team2": {
      "name": "SINNERS"
    },
    "kickoff_date": "live",
    "kickoff_time": "live",
    "match_date": "live",
    "match_time": "live",
    "duration": "live",
    "servers": [
      {
        "url": "https://multi.govoet.my.id/?iframe=aHR0cHM6Ly9zcG9ydC5pbnBsYXluZXQudGVjaC9saXZlc3RyZWFtLmh0bWw/c3JjPWFIUjBjSE02THk5d2JHRjVaWEl1ZEhkcGRHTm9MblIyTHo5amFHRnVibVZzUFhSd1oxOWpjeVp3WVhKbGJuUTlaR1Z0Ynk1cGJuQnNZWGx1WlhRdVkyOXQ=",
        "label": "CH-NA"
      }
    ]
  },
  {
    "id": "Bangkok-Utd-Tha-Persib-Bandung-Ina",
    "league": "AFC Champions League 2 - Round 2",
    "team1": {
      "name": "Bangkok Utd (Tha)",
      "logo": "https://static.flashscore.com/res/image/data/Y1NdwVVg-WGasveDI.png"
    },
    "team2": {
      "name": "Persib Bandung (Ina)",
      "logo": "https://static.flashscore.com/res/image/data/QuGrSijl-fXN2TGqm.png"
    },
    "kickoff_date": "2025-10-01",
    "kickoff_time": "19:15",
    "match_date": "2025-10-01",
    "match_time": "19:05",
    "duration": "3.5",
    "icon": "https://via.placeholder.com/30.png?text=Soccer",
    "servers": [
      {
        "url": "https://multi.govoet.my.id/?shaka=sport2baltic",
        "label": "CH-LT"
      },
      {
        "url": "https://list-govoet.blogspot.com/p/embed1.html",
        "label": "CH-ID"
      },
      {
        "url": "https://multi.govoet.my.id/?hls=aHR0cHM6Ly9zdHJlYW0udGl0YW5saXZlc2NvcmUuY29tL2xpdmUvTFhTQ09SRS0xMDAwMDAwNTMubTN1OA==",
        "label": "CH-ID"
      }
    ]
  }
]