[
  {
    "id": "Indonesia-SuperLeague-PersijapJepara-SemenPadang",
    "league": "Indonesia - Super League",
    "team1": {
      "name": "Persijap Jepara"
    },
    "team2": {
      "name": "Semen Padang"
    },
    "kickoff_date": "2025-11-20",
    "kickoff_time": "15:30",
    "match_date": "2025-11-20",
    "match_time": "15:30",
    "duration": "3.5",
    "servers": []
  },
  {
    "id": "Indonesia-SuperLeague-PersijaJakarta-PersikKediri",
    "league": "Indonesia - Super League",
    "team1": {
      "name": "Persija Jakarta"
    },
    "team2": {
      "name": "Persik Kediri"
    },
    "kickoff_date": "2025-11-20",
    "kickoff_time": "19:00",
    "match_date": "2025-11-20",
    "match_time": "19:00",
    "duration": "3.5",
    "servers": []
  },
  {
    "id": "Indonesia-SuperLeague-PSMMakassar-PSBSBiakNumfor",
    "league": "Indonesia - Super League",
    "team1": {
      "name": "PSM Makassar"
    },
    "team2": {
      "name": "PSBS Biak Numfor"
    },
    "kickoff_date": "2025-11-21",
    "kickoff_time": "15:30",
    "match_date": "2025-11-21",
    "match_time": "15:30",
    "duration": "3.5",
    "servers": []
  },
  {
    "id": "Indonesia-SuperLeague-PersibBandung-DewaUnited",
    "league": "Indonesia - Super League",
    "team1": {
      "name": "Persib Bandung"
    },
    "team2": {
      "name": "Dewa United"
    },
    "kickoff_date": "2025-11-21",
    "kickoff_time": "19:00",
    "match_date": "2025-11-21",
    "match_time": "19:00",
    "duration": "3.5",
    "servers": []
  }
]